{
  "generatedAt": "2026-07-16T09:28:20.616Z",
  "stats": {
    "analysed": 800,
    "windowHours": 168,
    "sources": 69
  },
  "findings": {
    "tendancesLourdes": [
      {
        "axe": "thematique",
        "cle": "P",
        "libelle": "Politique interne & gouvernance",
        "volume": 95,
        "base": 94.2,
        "direction": "stable"
      },
      {
        "axe": "thematique",
        "cle": "E",
        "libelle": "Économie & ressources",
        "volume": 75,
        "base": 86.2,
        "direction": "stable"
      },
      {
        "axe": "thematique",
        "cle": "S",
        "libelle": "Sécurité & défense",
        "volume": 66,
        "base": 66.5,
        "direction": "stable"
      },
      {
        "axe": "thematique",
        "cle": "D",
        "libelle": "Diplomatie & alliances",
        "volume": 48,
        "base": 51.9,
        "direction": "stable"
      },
      {
        "axe": "thematique",
        "cle": "J",
        "libelle": "Justice & droit international",
        "volume": 25,
        "base": 26.6,
        "direction": "stable"
      },
      {
        "axe": "zone",
        "cle": 1,
        "libelle": "1. Sahel & AO franco.",
        "volume": 83,
        "base": 95.1,
        "direction": "stable"
      },
      {
        "axe": "zone",
        "cle": 2,
        "libelle": "2. AO anglo. & côtière",
        "volume": 52,
        "base": 56.9,
        "direction": "stable"
      },
      {
        "axe": "zone",
        "cle": 7,
        "libelle": "7. Maghreb & Afr. Nord",
        "volume": 36,
        "base": 27.5,
        "direction": "hausse"
      },
      {
        "axe": "zone",
        "cle": 4,
        "libelle": "4. Grands Lacs",
        "volume": 14,
        "base": 12.7,
        "direction": "stable"
      }
    ],
    "signauxFaibles": [
      {
        "zone": "18. Amérique du Sud",
        "thematique": "Diplomatie & alliances",
        "code": "D",
        "volume": 3,
        "pertinence": "○",
        "exemple": "Why FIFA may sanction Argentina after World Cup win over England"
      },
      {
        "zone": "12. Asie du Sud",
        "thematique": "Maritime & océanique",
        "code": "M",
        "volume": 2,
        "pertinence": "●",
        "exemple": "Pakistan urges US, Iran to 'end violence', resume technical-level talks"
      },
      {
        "zone": "3. Afrique centrale",
        "thematique": "Information & influence",
        "code": "I",
        "volume": 1,
        "pertinence": "●",
        "exemple": "Cameroun : »Négligence, abandon » d’un patient au CURY, l’Hôpital Général de Yaoundé rassure"
      },
      {
        "zone": "6. Afrique australe",
        "thematique": "Politique interne & gouvernance",
        "code": "P",
        "volume": 1,
        "pertinence": "○",
        "exemple": "Sofia Scialoja, chercheuse en relations internationales : « La xénophobie est contradictoire avec les fondements identitaires de l’Afrique du Sud post-apartheid »"
      },
      {
        "zone": "10. Europe orient. & Balkans",
        "thematique": "Justice & droit international",
        "code": "J",
        "volume": 1,
        "pertinence": "●",
        "exemple": "Ukrainian foreign minister says potential Zelenskyy-Putin talks could be held in Türkiye"
      },
      {
        "zone": "6. Afrique australe",
        "thematique": "Sécurité & défense",
        "code": "S",
        "volume": 1,
        "pertinence": "○",
        "exemple": "Antoine Rajerison, le député des paysans qui brave la junte militaire au pouvoir à Madagascar"
      },
      {
        "zone": "2. AO anglo. & côtière",
        "thematique": "Humanitaire & social",
        "code": "H",
        "volume": 1,
        "pertinence": "●",
        "exemple": "KTU and CryoChain Ghana Ltd explore strategic partnership to build cold chain AgriTech hub"
      },
      {
        "zone": "10. Europe orient. & Balkans",
        "thematique": "Information & influence",
        "code": "I",
        "volume": 1,
        "pertinence": "●",
        "exemple": "Ukraine: Russian-Run Schools Violate Children’s Rights"
      }
    ],
    "ruptures": [
      {
        "type": "evenement",
        "zone": "8. Moyen-Orient",
        "thematique": "Maritime & océanique",
        "titre": "Iran warns Strait of Hormuz is a 'red line' and will resist until the end",
        "source": "Al-Monitor",
        "cote": "F2",
        "lien": "https://www.al-monitor.com/originals/2026/07/iran-warns-strait-hormuz-red-line-and-will-resist-until-end"
      },
      {
        "type": "evenement",
        "zone": "8. Moyen-Orient",
        "thematique": "Sécurité & défense",
        "titre": "U.S. airstrikes hit northern Iran as it disables ship trying to run blockade",
        "source": "The Hindu (Inde)",
        "cote": "F2",
        "lien": "https://www.thehindu.com/news/international/iran-us-conflict-tehran-air-strikes-strait-of-hormuz-trump/article71228681.ece"
      },
      {
        "type": "evenement",
        "zone": "Zone null",
        "thematique": "Maritime & océanique",
        "titre": "Fewer vessels travel through Hormuz after US resumes blockade",
        "source": "Al-Monitor",
        "cote": "F2",
        "lien": "https://www.al-monitor.com/originals/2026/07/fewer-vessels-travel-through-hormuz-after-us-resumes-blockade"
      },
      {
        "type": "evenement",
        "zone": "Zone null",
        "thematique": "Humanitaire & social",
        "titre": "À seulement 15 ans, elle massacre 5 membres de sa famille avec son petit ami",
        "source": "Malijet",
        "cote": "F2",
        "lien": "https://malijet.com/insolite-kabako/310624-a-seulement-15-ans-elle-massacre-5-membres-de-sa-famille-av.html"
      },
      {
        "type": "evenement",
        "zone": "Zone null",
        "thematique": null,
        "titre": "Families of 43 victims await verdict in Genoa bridge disaster",
        "source": "BBC World",
        "cote": "B2",
        "lien": "https://www.bbc.co.uk/news/articles/c20y00712ezo?at_medium=RSS&at_campaign=rss"
      },
      {
        "type": "evenement",
        "zone": "18. Amérique du Sud",
        "thematique": "Politique interne & gouvernance",
        "titre": "Au Venezuela, le bilan du double séisme monte à au moins 4 829 morts",
        "source": "Libération International",
        "cote": "C2",
        "lien": "https://www.liberation.fr/international/amerique/au-venezuela-le-bilan-du-double-seisme-monte-a-pres-de-3-000-morts-20260705_X7LWUOQT3ZBFXA2MHCBRQXUOUM/"
      },
      {
        "type": "pic",
        "zone": "4. Grands Lacs",
        "thematique": "Diplomatie & alliances",
        "volume": 5,
        "base": 0.9
      },
      {
        "type": "pic",
        "zone": "7. Maghreb & Afr. Nord",
        "thematique": "Diplomatie & alliances",
        "volume": 7,
        "base": 2.5
      }
    ],
    "recompositions": []
  },
  "notesParZone": [
    {
      "zone": "1. Sahel & AO franco.",
      "thematiquesDominantes": [
        "Sécurité & défense",
        "Diplomatie & alliances",
        "Politique interne & gouvernance"
      ],
      "faits": [
        {
          "titre": "Burkina: le chef de la diplomatie burkinabè échange avec le président de la Commission de l’UA sur la coopération bilatérale",
          "source": "AIB — Agence Information BF",
          "cote": "A1",
          "lien": "https://www.aib.media/burkina-le-chef-de-la-diplomatie-burkinabe-echange-avec-le-president-de-la-commission-de-lua-sur-la-cooperation-bilaterale/",
          "theme": "D"
        },
        {
          "titre": "Coordination air-sol : De Yensé à Diabatou, l’armée burkinabè met en déroute les groupes armés au Nord et à l’Est",
          "source": "Net Afrique (BF)",
          "cote": "F2",
          "lien": "https://netafrique.net/coordination-air-sol-de-yense-a-diabatou-larmee-burkinabe-met-en-deroute-les-groupes-armes-au-nord-et-a-lest/",
          "theme": "S"
        },
        {
          "titre": "Oudalan: la commune de Gorom-Gorom inaugure le « Rond-point de la Paix » à l’effigie d’un dromadaire pour valoriser son identité culturelle",
          "source": "AIB — Agence Information BF",
          "cote": "C2",
          "lien": "https://www.aib.media/oudalan-la-commune-de-gorom-gorom-inaugure-le-rond-point-de-la-paix-a-leffigie-dun-dromadaire-pour-valoriser-son-identite-culturelle/",
          "theme": "P"
        },
        {
          "titre": "Poni/Tourisme éducatif: des élèves de l’école annexe de Gaoua à la découverte du patrimoine historique de Batié",
          "source": "AIB — Agence Information BF",
          "cote": "C2",
          "lien": "https://www.aib.media/poni-tourisme-educatif-des-eleves-de-lecole-annexe-de-gaoua-a-la-decouverte-du-patrimoine-historique-de-batie/",
          "theme": "S"
        },
        {
          "titre": "Burkina Faso : Les Forces combattantes consolident leurs avancées territoriales en nettoyant plusieurs repaires terroristes",
          "source": "Net Afrique (BF)",
          "cote": "F1",
          "lien": "https://netafrique.net/burkina-faso-les-forces-combattantes-consolident-leurs-avancees-territoriales-en-nettoyant-plusieurs-repaires-terroristes/",
          "theme": "S"
        }
      ],
      "lectureStructuree": "Faits marquants : « Burkina: le chef de la diplomatie burkinabè échange avec le président de la Commission de l’UA sur la coopération bilatérale » (AIB — Agence Information BF) ; « Coordination air-sol : De Yensé à Diabatou, l’armée burkinabè met en déroute les groupes armés au Nord et à l’Est » (Net Afrique (BF)) ; « Oudalan: la commune de Gorom-Gorom inaugure le « Rond-point de la Paix » à l’effigie d’un dromadaire pour valoriser son identité culturelle » (AIB — Agence Information BF).\nThématiques actives : Sécurité & défense, Diplomatie & alliances, Politique interne & gouvernance (83 signaux sur la période).\nLecture : la zone pèse sur l'AES via ces dynamiques ; surveiller les signaux de bascule et leurs effets directs/indirects (sécurité, corridors, diplomatie, prix).",
      "confiance": "eleve",
      "proseIA": null
    },
    {
      "zone": "2. AO anglo. & côtière",
      "thematiquesDominantes": [
        "Économie & ressources",
        "Politique interne & gouvernance"
      ],
      "faits": [
        {
          "titre": "Ghana’s informal cross-border trade hits GH¢31bn",
          "source": "MyJoyOnline (Ghana)",
          "cote": "F6",
          "lien": "https://www.myjoyonline.com/ghanas-informal-cross-border-trade-hits-gh%c2%a231bn/",
          "theme": "E"
        },
        {
          "titre": "Stock market experts optimistic on H2’26 but warn investors",
          "source": "Vanguard (Nigeria)",
          "cote": "F2",
          "lien": "https://www.vanguardngr.com/2026/07/stock-market-experts-optimistic-on-h226-but-warn-investors/",
          "theme": "E"
        },
        {
          "titre": "CAC begins sixth batch of company strike-off, targets 100,000 companies",
          "source": "Premium Times (Nigeria)",
          "cote": "F2",
          "lien": "https://www.premiumtimesng.com/business/business-news/895765-cac-begins-sixth-batch-of-company-strike-off-targets-100000-companies.html",
          "theme": null
        },
        {
          "titre": "Makoko waterfront reclamation in Lagos approved by FG, state govt – Official",
          "source": "Premium Times (Nigeria)",
          "cote": "F2",
          "lien": "https://www.premiumtimesng.com/news/top-news/895757-makoko-waterfront-reclamation-in-lagos-approved-by-fg-state-govt-official.html",
          "theme": null
        },
        {
          "titre": "2027: Christians now more comfortable with Muslim-Muslim ticket – APC chieftain",
          "source": "Vanguard (Nigeria)",
          "cote": "F2",
          "lien": "https://www.vanguardngr.com/2026/07/2027-christians-now-more-comfortable-with-muslim-muslim-ticket-apc-chieftain/",
          "theme": "P"
        }
      ],
      "lectureStructuree": "Faits marquants : « Ghana’s informal cross-border trade hits GH¢31bn » (MyJoyOnline (Ghana)) ; « Stock market experts optimistic on H2’26 but warn investors » (Vanguard (Nigeria)) ; « CAC begins sixth batch of company strike-off, targets 100,000 companies » (Premium Times (Nigeria)).\nThématiques actives : Économie & ressources, Politique interne & gouvernance (52 signaux sur la période).\nLecture : la zone pèse sur l'AES via ces dynamiques ; surveiller les signaux de bascule et leurs effets directs/indirects (sécurité, corridors, diplomatie, prix).",
      "confiance": "eleve",
      "proseIA": null
    },
    {
      "zone": "7. Maghreb & Afr. Nord",
      "thematiquesDominantes": [
        "Économie & ressources",
        "Diplomatie & alliances"
      ],
      "faits": [
        {
          "titre": "Air France, Brussels Airlines, Air Algérie… La réconciliation entre Bamako et Alger, une aubaine pour l’aérien ?",
          "source": "Jeune Afrique",
          "cote": "B2",
          "lien": "https://www.jeuneafrique.com/1818435/economie-entreprises/air-france-brussels-airlines-air-algerie-la-reconciliation-entre-bamako-et-alger-une-aubaine-pour-laerien/",
          "theme": "D"
        },
        {
          "titre": "Relations France-Sahel: «Rabat essaye de tout cœur de jouer un rôle» dans l'amélioration des liens",
          "source": "RFI Afrique",
          "cote": "A2",
          "lien": "https://www.rfi.fr/fr/podcasts/le-grand-invit%C3%A9-afrique/20260716-relations-france-sahel-rabat-essaye-de-tout-c%C5%93ur-de-jouer-un-r%C3%B4le-dans-l-am%C3%A9lioration-des-liens",
          "theme": "E"
        },
        {
          "titre": "Education et emploi | Le match Tunisie-Maroc que Carthage est en train de perdre",
          "source": "Kapitalis (Tunisie)",
          "cote": "F2",
          "lien": "https://kapitalis.com/tunisie/2026/07/16/education-et-emploi-le-match-maroc-tunisie-que-carthage-est-en-train-de-perdre/",
          "theme": "E"
        },
        {
          "titre": "Maroc-France : le Premier ministre Sébastien Lecornu à Rabat pour consolider un partenariat au beau fixe",
          "source": "Jeune Afrique",
          "cote": "B1",
          "lien": "https://www.jeuneafrique.com/1822420/politique/maroc-france-le-premier-ministre-sebastien-lecornu-a-rabat-pour-consolider-un-partenariat-au-beau-fixe/",
          "theme": "E"
        },
        {
          "titre": "Maroc : les prix du gasoil et de l’essence repartent à la hausse",
          "source": "Hespress (Maroc, FR)",
          "cote": "F2",
          "lien": "https://fr.hespress.com/481560-maroc-les-prix-du-gasoil-et-de-lessence-repartent-a-la-hausse.html",
          "theme": "E"
        }
      ],
      "lectureStructuree": "Faits marquants : « Air France, Brussels Airlines, Air Algérie… La réconciliation entre Bamako et Alger, une aubaine pour l’aérien ? » (Jeune Afrique) ; « Relations France-Sahel: «Rabat essaye de tout cœur de jouer un rôle» dans l'amélioration des liens » (RFI Afrique) ; « Education et emploi | Le match Tunisie-Maroc que Carthage est en train de perdre » (Kapitalis (Tunisie)).\nThématiques actives : Économie & ressources, Diplomatie & alliances (36 signaux sur la période).\nLecture : la zone pèse sur l'AES via ces dynamiques ; surveiller les signaux de bascule et leurs effets directs/indirects (sécurité, corridors, diplomatie, prix).",
      "confiance": "eleve",
      "proseIA": null
    }
  ],
  "notesProspectives": [
    {
      "zone": "1. Sahel & AO franco.",
      "hypothese": "Si la dynamique « 1. Sahel & AO franco. » (stable) se poursuit a 3-6 mois, l'impact sur l'AES s'accentue.",
      "signauxASurveiller": [
        "Frequence et localisation des incidents",
        "Reactions diplomatiques (CEDEAO/UA/ONU)",
        "Etat des corridors logistiques",
        "Prix (or, carburant, cereales)"
      ],
      "confiance": "faible",
      "proseIA": null
    },
    {
      "zone": "2. AO anglo. & côtière",
      "hypothese": "Si la dynamique « 2. AO anglo. & côtière » (stable) se poursuit a 3-6 mois, l'impact sur l'AES s'accentue.",
      "signauxASurveiller": [
        "Frequence et localisation des incidents",
        "Reactions diplomatiques (CEDEAO/UA/ONU)",
        "Etat des corridors logistiques",
        "Prix (or, carburant, cereales)"
      ],
      "confiance": "faible",
      "proseIA": null
    },
    {
      "zone": "7. Maghreb & Afr. Nord",
      "hypothese": "Si la dynamique « 7. Maghreb & Afr. Nord » (hausse) se poursuit a 3-6 mois, l'impact sur l'AES s'accentue.",
      "signauxASurveiller": [
        "Frequence et localisation des incidents",
        "Reactions diplomatiques (CEDEAO/UA/ONU)",
        "Etat des corridors logistiques",
        "Prix (or, carburant, cereales)"
      ],
      "confiance": "moyen",
      "proseIA": null
    }
  ],
  "etudesThematiques": [
    {
      "code": "P",
      "libelle": "Politique interne & gouvernance",
      "volume": 95,
      "direction": "stable",
      "faitsSaillants": [
        {
          "titre": "Oudalan: la commune de Gorom-Gorom inaugure le « Rond-point de la Paix » à l’effigie d’un dromadaire pour valoriser son identité culturelle",
          "source": "AIB — Agence Information BF",
          "cote": "C2",
          "lien": "https://www.aib.media/oudalan-la-commune-de-gorom-gorom-inaugure-le-rond-point-de-la-paix-a-leffigie-dun-dromadaire-pour-valoriser-son-identite-culturelle/"
        },
        {
          "titre": "Concours directs de la Fonction publique 2026 : A Djibo, le Gouvernement réaffirme la présence de l’Etat et son engagement à garantir l’égalité des chances",
          "source": "Net Afrique (BF)",
          "cote": "F1",
          "lien": "https://netafrique.net/concours-directs-de-la-fonction-publique-2026-a-djibo-le-gouvernement-reaffirme-la-presence-de-letat-et-son-engagement-a-garantir-legalite-des-chances/"
        },
        {
          "titre": "Burkina Faso : 440 formateurs mobilisés pour l’immersion patriotique obligatoire 2026",
          "source": "Net Afrique (BF)",
          "cote": "F1",
          "lien": "https://netafrique.net/burkina-faso-440-formateurs-mobilises-pour-limmersion-patriotique-obligatoire-2026/"
        },
        {
          "titre": "Tchad: le Président annonce la suppression des visas d’entrée sur le territoire pour tous les Africains dès le 1er janvier 2027",
          "source": "AIB — Agence Information BF",
          "cote": "C2",
          "lien": "https://www.aib.media/tchad-le-president-annonce-la-suppression-des-visas-dentree-sur-le-territoire-pour-tous-les-africains-des-le-1er-janvier-2027/"
        },
        {
          "titre": "Ouagadougou : le président de la Commission de l'UA échange avec les autorités burkinabè",
          "source": "Malijet",
          "cote": "A1",
          "lien": "https://malijet.com/actualite-sur-afrique/310619-ouagadougou-le-president-de-la-commission-de-lua-echange.html"
        }
      ],
      "lecture": "Politique interne & gouvernance : 95 signaux sur la période (tendance stable). Faits marquants : « Oudalan: la commune de Gorom-Gorom inaugure le « Rond-point de la Paix » à l’effigie d’un dromadaire pour valoriser son identité culturelle » (AIB — Agence Information BF) ; « Concours directs de la Fonction publique 2026 : A Djibo, le Gouvernement réaffirme la présence de l’Etat et son engagement à garantir l’égalité des chances » (Net Afrique (BF)) ; « Burkina Faso : 440 formateurs mobilisés pour l’immersion patriotique obligatoire 2026 » (Net Afrique (BF)).",
      "blocs": [
        "afrique (30)",
        "occident_fr (20)",
        "bf_local (12)",
        "autre (10)"
      ],
      "sources": [
        "MyJoyOnline (Ghana)",
        "Net Afrique (BF)",
        "Dawn (Pakistan)",
        "France 24",
        "The Hindu (Inde)"
      ],
      "proseIA": null
    },
    {
      "code": "E",
      "libelle": "Économie & ressources",
      "volume": 75,
      "direction": "stable",
      "faitsSaillants": [
        {
          "titre": "EBOMAF-GABON : 485 km de routes pour construire l’avenir",
          "source": "Net Afrique (BF)",
          "cote": "F2",
          "lien": "https://netafrique.net/ebomaf-gabon-485-km-de-routes-pour-construire-lavenir/"
        },
        {
          "titre": "Mois artistique et culturel : une première édition réussie dans la transmission des valeurs aux enfants",
          "source": "AIB — Agence Information BF",
          "cote": "A1",
          "lien": "https://www.aib.media/mois-artistique-et-culturel-une-premiere-edition-reussie-dans-la-transmission-des-valeurs-aux-enfants/"
        },
        {
          "titre": "Complexe hôtelier Entente Burkina Faso: la réalisation du projet au cœur d’une rencontre",
          "source": "Sidwaya",
          "cote": "C1",
          "lien": "https://www.sidwaya.info/complexe-hotelier-entente-burkina-faso-la-realisation-du-projet-au-coeur-dune-rencontre/"
        },
        {
          "titre": "Burkina Faso : NEEMBA Burkina offre 60 bourses aux étudiants de l’UTS",
          "source": "Faso7",
          "cote": "F2",
          "lien": "https://faso7.com/2026/07/15/burkina-faso-neemba-burkina-offre-60-bourses-aux-etudiants-de-luts/"
        },
        {
          "titre": "Burkina Faso-Conseil de l’Entente : Vers la création d’un complexe hôtelier de haut standing à Ouaga 2000",
          "source": "Net Afrique (BF)",
          "cote": "F1",
          "lien": "https://netafrique.net/burkina-faso-conseil-de-lentente-vers-la-creation-dun-complexe-hotelier-de-haut-standing-a-ouaga-2000/"
        }
      ],
      "lecture": "Économie & ressources : 75 signaux sur la période (tendance stable). Faits marquants : « EBOMAF-GABON : 485 km de routes pour construire l’avenir » (Net Afrique (BF)) ; « Mois artistique et culturel : une première édition réussie dans la transmission des valeurs aux enfants » (AIB — Agence Information BF) ; « Complexe hôtelier Entente Burkina Faso: la réalisation du projet au cœur d’une rencontre » (Sidwaya).",
      "blocs": [
        "afrique (30)",
        "occident_fr (12)",
        "bf_local (9)",
        "autre (9)"
      ],
      "sources": [
        "Vanguard (Nigeria)",
        "Le Soleil (Sénégal)",
        "MyJoyOnline (Ghana)",
        "RFI Afrique",
        "Hespress (Maroc, FR)"
      ],
      "proseIA": null
    },
    {
      "code": "S",
      "libelle": "Sécurité & défense",
      "volume": 66,
      "direction": "stable",
      "faitsSaillants": [
        {
          "titre": "Coordination air-sol : De Yensé à Diabatou, l’armée burkinabè met en déroute les groupes armés au Nord et à l’Est",
          "source": "Net Afrique (BF)",
          "cote": "F2",
          "lien": "https://netafrique.net/coordination-air-sol-de-yense-a-diabatou-larmee-burkinabe-met-en-deroute-les-groupes-armes-au-nord-et-a-lest/"
        },
        {
          "titre": "Poni/Tourisme éducatif: des élèves de l’école annexe de Gaoua à la découverte du patrimoine historique de Batié",
          "source": "AIB — Agence Information BF",
          "cote": "C2",
          "lien": "https://www.aib.media/poni-tourisme-educatif-des-eleves-de-lecole-annexe-de-gaoua-a-la-decouverte-du-patrimoine-historique-de-batie/"
        },
        {
          "titre": "Burkina Faso : Les Forces combattantes consolident leurs avancées territoriales en nettoyant plusieurs repaires terroristes",
          "source": "Net Afrique (BF)",
          "cote": "F1",
          "lien": "https://netafrique.net/burkina-faso-les-forces-combattantes-consolident-leurs-avancees-territoriales-en-nettoyant-plusieurs-repaires-terroristes/"
        },
        {
          "titre": "18e édition d’engagement féminin : promotion du leadership de la femme africaine à travers la danse contemporaine",
          "source": "Sidwaya",
          "cote": "C2",
          "lien": "https://www.sidwaya.info/18e-edition-dengagement-feminin-promotion-du-leadership-de-la-femme-africaine-a-travers-la-danse-contemporaine-2/"
        },
        {
          "titre": "Les nouvelles du front: les Forces combattantes consolident leurs avancées territoriales en nettoyant plusieurs repaires terroristes",
          "source": "Sidwaya",
          "cote": "C1",
          "lien": "https://www.sidwaya.info/les-forces-combattantes-consolident-leurs-avancees-territoriales-en-nettoyant-plusieurs-repaires-terroristes/"
        }
      ],
      "lecture": "Sécurité & défense : 66 signaux sur la période (tendance stable). Faits marquants : « Coordination air-sol : De Yensé à Diabatou, l’armée burkinabè met en déroute les groupes armés au Nord et à l’Est » (Net Afrique (BF)) ; « Poni/Tourisme éducatif: des élèves de l’école annexe de Gaoua à la découverte du patrimoine historique de Batié » (AIB — Agence Information BF) ; « Burkina Faso : Les Forces combattantes consolident leurs avancées territoriales en nettoyant plusieurs repaires terroristes » (Net Afrique (BF)).",
      "blocs": [
        "afrique (14)",
        "russie (11)",
        "occident_fr (10)",
        "bf_local (8)"
      ],
      "sources": [
        "TASS (Russie, EN)",
        "Press TV (Iran)",
        "El País (Espagne, ES)",
        "Dawn (Pakistan)",
        "Vanguard (Nigeria)"
      ],
      "proseIA": null
    },
    {
      "code": "D",
      "libelle": "Diplomatie & alliances",
      "volume": 48,
      "direction": "stable",
      "faitsSaillants": [
        {
          "titre": "Burkina: le chef de la diplomatie burkinabè échange avec le président de la Commission de l’UA sur la coopération bilatérale",
          "source": "AIB — Agence Information BF",
          "cote": "A1",
          "lien": "https://www.aib.media/burkina-le-chef-de-la-diplomatie-burkinabe-echange-avec-le-president-de-la-commission-de-lua-sur-la-cooperation-bilaterale/"
        },
        {
          "titre": "Expulsion des diplomates de l’UE : en toute souveraineté !",
          "source": "Sidwaya",
          "cote": "C2",
          "lien": "https://www.sidwaya.info/expulsion-des-diplomates-de-lue-en-toute-souverainete/"
        },
        {
          "titre": "Zoundwéogo/Excellence Scolaire : des meilleurs élèves de l’école de Doncin reçoivent des vélos et des kits scolaires",
          "source": "AIB — Agence Information BF",
          "cote": "C2",
          "lien": "https://www.aib.media/zoundweogo-excellence-scolaire-des-meilleurs-eleves-de-lecole-de-doncin-recoivent-des-velos-et-des-kits-scolaires/"
        },
        {
          "titre": "Air France, Brussels Airlines, Air Algérie… La réconciliation entre Bamako et Alger, une aubaine pour l’aérien ?",
          "source": "Jeune Afrique",
          "cote": "B2",
          "lien": "https://www.jeuneafrique.com/1818435/economie-entreprises/air-france-brussels-airlines-air-algerie-la-reconciliation-entre-bamako-et-alger-une-aubaine-pour-laerien/"
        },
        {
          "titre": "Les rastafaris d’Afrique toujours en quête de reconnaissance",
          "source": "RFI Afrique",
          "cote": "A2",
          "lien": "https://www.rfi.fr/fr/afrique/20260715-les-rastafaris-d-afrique-toujours-en-qu%C3%AAte-de-reconnaissance"
        }
      ],
      "lecture": "Diplomatie & alliances : 48 signaux sur la période (tendance stable). Faits marquants : « Burkina: le chef de la diplomatie burkinabè échange avec le président de la Commission de l’UA sur la coopération bilatérale » (AIB — Agence Information BF) ; « Expulsion des diplomates de l’UE : en toute souveraineté ! » (Sidwaya) ; « Zoundwéogo/Excellence Scolaire : des meilleurs élèves de l’école de Doncin reçoivent des vélos et des kits scolaires » (AIB — Agence Information BF).",
      "blocs": [
        "afrique (17)",
        "occident_fr (7)",
        "russie (6)",
        "occident_us (5)"
      ],
      "sources": [
        "RFI Afrique",
        "Radio Okapi (RDC)",
        "Kapitalis (Tunisie)",
        "TASS (Russie, EN)",
        "AIB — Agence Information BF"
      ],
      "proseIA": null
    }
  ],
  "byConflict": {
    "c_aes": {
      "id": "c_aes",
      "name": "Sahel/AES",
      "volume": 91,
      "themesDominants": [
        "Sécurité & défense",
        "Diplomatie & alliances",
        "Économie & ressources"
      ],
      "faits": [
        {
          "titre": "Burkina: le chef de la diplomatie burkinabè échange avec le président de la Commission de l’UA sur la coopération bilatérale",
          "source": "AIB — Agence Information BF",
          "cote": "A1",
          "lien": "https://www.aib.media/burkina-le-chef-de-la-diplomatie-burkinabe-echange-avec-le-president-de-la-commission-de-lua-sur-la-cooperation-bilaterale/",
          "theme": "D"
        },
        {
          "titre": "Coordination air-sol : De Yensé à Diabatou, l’armée burkinabè met en déroute les groupes armés au Nord et à l’Est",
          "source": "Net Afrique (BF)",
          "cote": "F2",
          "lien": "https://netafrique.net/coordination-air-sol-de-yense-a-diabatou-larmee-burkinabe-met-en-deroute-les-groupes-armes-au-nord-et-a-lest/",
          "theme": "S"
        },
        {
          "titre": "EBOMAF-GABON : 485 km de routes pour construire l’avenir",
          "source": "Net Afrique (BF)",
          "cote": "F2",
          "lien": "https://netafrique.net/ebomaf-gabon-485-km-de-routes-pour-construire-lavenir/",
          "theme": "E"
        },
        {
          "titre": "Oudalan: la commune de Gorom-Gorom inaugure le « Rond-point de la Paix » à l’effigie d’un dromadaire pour valoriser son identité culturelle",
          "source": "AIB — Agence Information BF",
          "cote": "C2",
          "lien": "https://www.aib.media/oudalan-la-commune-de-gorom-gorom-inaugure-le-rond-point-de-la-paix-a-leffigie-dun-dromadaire-pour-valoriser-son-identite-culturelle/",
          "theme": "P"
        },
        {
          "titre": "Poni/Tourisme éducatif: des élèves de l’école annexe de Gaoua à la découverte du patrimoine historique de Batié",
          "source": "AIB — Agence Information BF",
          "cote": "C2",
          "lien": "https://www.aib.media/poni-tourisme-educatif-des-eleves-de-lecole-annexe-de-gaoua-a-la-decouverte-du-patrimoine-historique-de-batie/",
          "theme": "S"
        },
        {
          "titre": "Burkina Faso : Les Forces combattantes consolident leurs avancées territoriales en nettoyant plusieurs repaires terroristes",
          "source": "Net Afrique (BF)",
          "cote": "F1",
          "lien": "https://netafrique.net/burkina-faso-les-forces-combattantes-consolident-leurs-avancees-territoriales-en-nettoyant-plusieurs-repaires-terroristes/",
          "theme": "S"
        }
      ],
      "enjeu": "Inventer un modèle politique africain qui combine souveraineté affichée et efficacité sécuritaire — sans y être encore parvenu.",
      "consequencesAES": "Maximale (priorité 1) : Le Burkina Faso EST le théâtre central de ce conflit. Toute analyse sahélienne est de facto une analyse burkinabè. : Le BF est l'État le plus exposé du trio AES en termes de pression jihadiste : ~40 % du territoire hors contrôle effectif, attaques mensuelles record en glissem…",
      "lectureStructuree": "SITUATION (live) — 91 dépêches sur la période, dominante : Sécurité & défense, Diplomatie & alliances, Économie & ressources.\nFaits saillants : « Burkina: le chef de la diplomatie burkinabè échange avec le président de la Commission de l’UA sur la coopération bilatérale » (AIB — Agence Information BF, cote A1) ; « Coordination air-sol : De Yensé à Diabatou, l’armée burkinabè met en déroute les groupes armés au Nord et à l’Est » (Net Afrique (BF), cote F2) ; « EBOMAF-GABON : 485 km de routes pour construire l’avenir » (Net Afrique (BF), cote F2).\n\nENJEU CENTRAL — Inventer un modèle politique africain qui combine souveraineté affichée et efficacité sécuritaire — sans y être encore parvenu.\n\nPOURQUOI — C'est la rupture géopolitique africaine la plus profonde depuis les indépendances. Elle redistribue les cartes de l'influence en Afrique de l'Ouest, fragilise la CEDEAO, ouvre la voie à de nouveaux partenaires (Russie, Chine, Iran, Turquie, Émirats), et pose la question de la viabilité du modèle militaro-plébiscitaire face à une menace jihadiste qui continue de progresser.\n\nIMPACT POUR L'AES — Maximale (priorité 1) : Le Burkina Faso EST le théâtre central de ce conflit. Toute analyse sahélienne est de facto une analyse burkinabè. : Le BF est l'État le plus exposé du trio AES en termes de pression jihadiste : ~40 % du territoire hors contrôle effectif, attaques mensuelles record en glissem…\n\nSCÉNARIOS —\n• Tendanciel — érosion lente (55%) : Les transitions tiennent par la force et la popularité urbaine, mais perdent du territoire rural. Wagner reste mais ne stabilise pas. JNIM consolide ses émirats. Attaques sur capitales sans les prendre. Sortie partielle F CFA, instabilité monétaire gérée.\n• Rupture — chute d'un État (25%) : Un État (probablement BF ou Mali) bascule : prise de capitale ou effondrement militaire complet. Gouvernement transitionnel forcé d'inclure jihadistes. Onde de choc régionale, exode massif, intervention extérieure non-occidentale possible (Égypte, Algérie).\n\nÀ SURVEILLER — Une attaque réussie sur Ouagadougou-centre ou Bamako (rupture systémique). ; L'extension côtière de la guerre (Bénin, Togo, Côte d'Ivoire). ; La sortie effective du F CFA et la naissance d'une monnaie AES.",
      "prospective": "12-24 mois : statu quo dégradé probable, perte de territoires ruraux, popularité urbaine maintenue.",
      "confiance": "eleve",
      "proseIA": null
    },
    "c_iran_il": {
      "id": "c_iran_il",
      "name": "Iran-Israël",
      "volume": 116,
      "themesDominants": [
        "Maritime & océanique",
        "Économie & ressources",
        "Sécurité & défense"
      ],
      "faits": [
        {
          "titre": "Appel solennel à l’engagement des Patriotes pour la République",
          "source": "Le Soleil (Sénégal)",
          "cote": "F2",
          "lien": "https://lesoleil.sn/actualites/politique/appel-solennel-a-lengagement-des-patriotes-pour-la-republique/",
          "theme": "E"
        },
        {
          "titre": "Iran warns Strait of Hormuz is a 'red line' and will resist until the end",
          "source": "Al-Monitor",
          "cote": "F2",
          "lien": "https://www.al-monitor.com/originals/2026/07/iran-warns-strait-hormuz-red-line-and-will-resist-until-end",
          "theme": "M"
        },
        {
          "titre": "U.S. airstrikes hit northern Iran as it disables ship trying to run blockade",
          "source": "The Hindu (Inde)",
          "cote": "F2",
          "lien": "https://www.thehindu.com/news/international/iran-us-conflict-tehran-air-strikes-strait-of-hormuz-trump/article71228681.ece",
          "theme": "S"
        },
        {
          "titre": "Fewer vessels travel through Hormuz after US resumes blockade",
          "source": "Al-Monitor",
          "cote": "F2",
          "lien": "https://www.al-monitor.com/originals/2026/07/fewer-vessels-travel-through-hormuz-after-us-resumes-blockade",
          "theme": "M"
        },
        {
          "titre": "Pakistan urges US, Iran to 'end violence', resume technical-level talks",
          "source": "Dawn (Pakistan)",
          "cote": "F1",
          "lien": "https://www.dawn.com/news/2015882/pakistan-urges-us-iran-to-end-violence-resume-technical-level-talks",
          "theme": "M"
        },
        {
          "titre": "Oil price reverses gains, falls 0.8% despite escalating US-Iran hostilities",
          "source": "Vanguard (Nigeria)",
          "cote": "F2",
          "lien": "https://www.vanguardngr.com/2026/07/oil-price-reverses-gains-falls-0-8-despite-escalating-us-iran-hostilities/",
          "theme": "E"
        }
      ],
      "enjeu": "La question nucléaire iranienne et la survie du régime des Pasdaran détermineront la stabilité régionale pour 20 ans.",
      "consequencesAES": "Élevée (impact indirect majeur) : Le BF n'est pas acteur direct mais subit la totalité des chocs économiques et géopolitiques de l'embrasement moyen-oriental. : Réseaux jihadistes sahéliens (JNIM, EIGS) bénéficient indirectement de l'effervescence post-Gaza : recrutement, financement Golfe, diffusio…",
      "lectureStructuree": "SITUATION (live) — 116 dépêches sur la période, dominante : Maritime & océanique, Économie & ressources, Sécurité & défense.\nFaits saillants : « Appel solennel à l’engagement des Patriotes pour la République » (Le Soleil (Sénégal), cote F2) ; « Iran warns Strait of Hormuz is a 'red line' and will resist until the end » (Al-Monitor, cote F2) ; « U.S. airstrikes hit northern Iran as it disables ship trying to run blockade » (The Hindu (Inde), cote F2).\n\nENJEU CENTRAL — La question nucléaire iranienne et la survie du régime des Pasdaran détermineront la stabilité régionale pour 20 ans.\n\nPOURQUOI — Le Moyen-Orient connaît sa plus profonde recomposition depuis 1979. L'affaiblissement de l'arc chiite ouvre une fenêtre incertaine : soit un nouvel ordre stable autour des puissances du Golfe, soit une escalade directe Iran-Israël-USA. Les chocs pétroliers potentiels via le détroit d'Ormuz frappent directement les économies importatrices comme le Burkina Faso. ⚠️ Certains éléments de cette analyse sont prospectifs — vérifiez avec les dernières sources IRIS/ICG.\n\nIMPACT POUR L'AES — Élevée (impact indirect majeur) : Le BF n'est pas acteur direct mais subit la totalité des chocs économiques et géopolitiques de l'embrasement moyen-oriental. : Réseaux jihadistes sahéliens (JNIM, EIGS) bénéficient indirectement de l'effervescence post-Gaza : recrutement, financement Golfe, diffusio…\n\nSCÉNARIOS —\n• Tendanciel — Iran affaibli, ordre US-saoudien (40%) : Régime iranien survit mais affaibli. Reconstruction proxies lente. Saoudiens dominent OPEC+ et arbitrent Levant. Israël intègre normalisation arabe (extension Abraham). Sahel et Russie reviennent par défaut.\n• Rupture — transition Pasdaran nucléaire (25%) : CGRI prend le pouvoir, sortie TNP, accélération bombe. Sanctions totales mais marché chinois maintenu. Course aux armements régionale (Saoudite, Turquie). Risque frappes israéliennes répétées.\n\nÀ SURVEILLER — L'état réel du programme nucléaire iranien (enrichissement résiduel ?). ; Le détroit d'Ormuz : toute fermeture déclencherait un choc pétrolier mondial. ; Le sort des sites nucléaires Fordo/Natanz : capacité résiduelle d'enrichir ?",
      "prospective": "6-12 mois : crise économique aiguë en Iran, possible accélération nucléaire clandestine.",
      "confiance": "eleve",
      "proseIA": null
    },
    "c_ukr": {
      "id": "c_ukr",
      "name": "Ukraine-Russie",
      "volume": 68,
      "themesDominants": [
        "Sécurité & défense",
        "Information & influence",
        "Économie & ressources"
      ],
      "faits": [
        {
          "titre": "Ukraine: Russian-Run Schools Violate Children’s Rights",
          "source": "Human Rights Watch",
          "cote": "F2",
          "lien": "https://www.hrw.org/news/2026/07/16/ukraine-russian-run-schools-violate-childrens-rights",
          "theme": "I"
        },
        {
          "titre": "La estrategia de Ucrania para estrangular Crimea: bombardeos con drones, ataques a infraestructuras y golpes psicológicos a las tropas rusas",
          "source": "El País (Espagne, ES)",
          "cote": "F2",
          "lien": "https://elpais.com/internacional/2026-07-16/la-estrategia-de-ucrania-para-estrangular-crimea-bombardeos-con-drones-ataques-a-infraestructuras-y-golpes-psicologicos-a-las-tropas-rusas.html",
          "theme": "S"
        },
        {
          "titre": "Depuis 2022 et le début de la guerre en Ukraine, l’électrification de l’Union n’a que très peu évolué",
          "source": "Le Grand Continent",
          "cote": "A2",
          "lien": "https://legrandcontinent.eu/fr/2026/07/16/depuis-2022-et-le-debut-de-la-guerre-en-ukraine-lelectrification-de-lunion-na-que-tres-peu-evolue/",
          "theme": "E"
        },
        {
          "titre": "Le Pentagone s’en prend aux puissances moyennes",
          "source": "Le Grand Continent",
          "cote": "A2",
          "lien": "https://legrandcontinent.eu/fr/2026/07/16/le-pentagone-sen-prend-aux-puissances-moyennes/",
          "theme": "S"
        },
        {
          "titre": "EN DIRECT, guerre en Ukraine : Kiev affirme avoir frappé deux pétroliers russes en mer Noire ; des manifestations dans le pays en soutien au ministre de la défense limogé",
          "source": "Le Monde International",
          "cote": "B1",
          "lien": "https://www.lemonde.fr/international/live/2026/07/16/en-direct-guerre-en-ukraine-kiev-affirme-avoir-frappe-deux-petroliers-russes-en-mer-noire-des-manifestations-dans-le-pays-en-soutien-au-ministre-de-la-defense-limoge_6722853_3210.html",
          "theme": "P"
        },
        {
          "titre": "Dismissal of Ukraine's popular defense minister draws intense criticism",
          "source": "NPR World",
          "cote": "A1",
          "lien": "https://www.npr.org/2026/07/16/nx-s1-5894781/dismissal-of-ukraines-popular-defense-minister-draws-intense-criticism",
          "theme": "S"
        }
      ],
      "enjeu": "L'Ukraine est trop grande pour être conquise et trop importante pour être abandonnée. Le conflit tend vers un blocage prolongé que personne ne sait résoudre.",
      "consequencesAES": "Élevée (Russie = partenaire stratégique BF) : La guerre russe en Ukraine engage directement le partenaire militaire principal du BF (Africa Corps) et structure ses capacités. : Africa Corps (héritier Wagner) : ~1 200-2 000 instructeurs/combattants au Mali, présence BF moins documentée mais croissant…",
      "lectureStructuree": "SITUATION (live) — 68 dépêches sur la période, dominante : Sécurité & défense, Information & influence, Économie & ressources.\nFaits saillants : « Ukraine: Russian-Run Schools Violate Children’s Rights » (Human Rights Watch, cote F2) ; « La estrategia de Ucrania para estrangular Crimea: bombardeos con drones, ataques a infraestructuras y golpes psicológicos a las tropas rusas » (El País (Espagne, ES), cote F2) ; « Depuis 2022 et le début de la guerre en Ukraine, l’électrification de l’Union n’a que très peu évolué » (Le Grand Continent, cote A2).\n\nENJEU CENTRAL — L'Ukraine est trop grande pour être conquise et trop importante pour être abandonnée. Le conflit tend vers un blocage prolongé que personne ne sait résoudre.\n\nPOURQUOI — C'est la première guerre européenne de haute intensité depuis 1945 et le test décisif de l'ordre international post-Guerre froide. Si la Russie obtient des concessions par la force, la frontière taïwanaise, sahélienne et caucasienne deviennent négociables par les armes. C'est aussi un test pour le réarmement européen et la crédibilité de l'OTAN sans soutien américain.\n\nIMPACT POUR L'AES — Élevée (Russie = partenaire stratégique BF) : La guerre russe en Ukraine engage directement le partenaire militaire principal du BF (Africa Corps) et structure ses capacités. : Africa Corps (héritier Wagner) : ~1 200-2 000 instructeurs/combattants au Mali, présence BF moins documentée mais croissant…\n\nSCÉNARIOS —\n• Tendanciel — gel armé (40%) : Trump impose cessez-le-feu sur ligne actuelle. Pas de reconnaissance Crimée/Donbass. Pas de garanties OTAN. Conflit gelé type Coréen. Reconstruction lente, militarisation pérenne.\n• Rupture — effondrement russe (20%) : Crise économique aiguë + défaite militaire ponctuelle + crise succession ouvrent transition. Risque mais aussi opportunité historique.\n\nÀ SURVEILLER — Les décrets de Trump sur l'aide militaire (effectif effectif sur 6 mois). ; L'évolution du front : reprise russe ou ukrainienne dans Sumy/Kharkiv/Donetsk. ; Les capacités économiques russes après 4 ans d'économie de guerre (taux d'intérêt 21%, démographie négative).",
      "prospective": "12-24 mois : forte probabilité de gel imposé par Trump sur la ligne actuelle, sans paix.",
      "confiance": "eleve",
      "proseIA": null
    },
    "c_gaza": {
      "id": "c_gaza",
      "name": "Gaza-Liban",
      "volume": 41,
      "themesDominants": [
        "Politique interne & gouvernance",
        "Maritime & océanique",
        "Logistique & corridors"
      ],
      "faits": [
        {
          "titre": "Pakistan urges US, Iran to 'end violence', resume technical-level talks",
          "source": "Dawn (Pakistan)",
          "cote": "F1",
          "lien": "https://www.dawn.com/news/2015882/pakistan-urges-us-iran-to-end-violence-resume-technical-level-talks",
          "theme": "M"
        },
        {
          "titre": "Syrian foils attempt to smuggle weapons, missiles to Hezbollah",
          "source": "Anadolu Agency (Turquie)",
          "cote": "A2",
          "lien": "https://www.aa.com.tr/en/middle-east/syrian-foils-attempt-to-smuggle-weapons-missiles-to-hezbollah/4000093",
          "theme": "L"
        },
        {
          "titre": "Education et emploi | Le match Tunisie-Maroc que Carthage est en train de perdre",
          "source": "Kapitalis (Tunisie)",
          "cote": "F2",
          "lien": "https://kapitalis.com/tunisie/2026/07/16/education-et-emploi-le-match-maroc-tunisie-que-carthage-est-en-train-de-perdre/",
          "theme": "E"
        },
        {
          "titre": "US House defeats bid to cut off Israel aid in vote dividing Democrats",
          "source": "Dawn (Pakistan)",
          "cote": "F1",
          "lien": "https://www.dawn.com/news/2015874/us-house-defeats-bid-to-cut-off-israel-aid-in-vote-dividing-democrats",
          "theme": "P"
        },
        {
          "titre": "Les « ambigüités créatrices » du Board of Peace",
          "source": "IRIS France",
          "cote": "A3",
          "lien": "https://www.iris-france.org/les-ambiguites-creatrices-du-board-of-peace/",
          "theme": "P"
        },
        {
          "titre": "Security forces foil suicide attack on military post in South Waziristan's Wana, kill 4 terrorists: sources",
          "source": "Dawn (Pakistan)",
          "cote": "A2",
          "lien": "https://www.dawn.com/news/2015848/security-forces-foil-suicide-attack-on-military-post-in-south-waziristans-wana-kill-4-terrorists-sources",
          "theme": "S"
        }
      ],
      "enjeu": "Sans horizon politique palestinien crédible (deux États ou alternative), aucun cessez-le-feu ne sera durable. Le « jour d'après » est la vraie question, pas le « jour pendant ».",
      "consequencesAES": "Modérée (impact diplomatique et symbolique) : Le BF n'est pas acteur direct mais la cause palestinienne structure la rhétorique anti-occidentale du régime et l'imaginaire panafricain. : Pas d'impact sécuritaire direct. Mais radicalisation idéologique via réseaux numériques mobilise jihadistes sahéli…",
      "lectureStructuree": "SITUATION (live) — 41 dépêches sur la période, dominante : Politique interne & gouvernance, Maritime & océanique, Logistique & corridors.\nFaits saillants : « Pakistan urges US, Iran to 'end violence', resume technical-level talks » (Dawn (Pakistan), cote F1) ; « Syrian foils attempt to smuggle weapons, missiles to Hezbollah » (Anadolu Agency (Turquie), cote A2) ; « Education et emploi | Le match Tunisie-Maroc que Carthage est en train de perdre » (Kapitalis (Tunisie), cote F2).\n\nENJEU CENTRAL — Sans horizon politique palestinien crédible (deux États ou alternative), aucun cessez-le-feu ne sera durable. Le « jour d'après » est la vraie question, pas le « jour pendant ».\n\nPOURQUOI — Au-delà du drame humanitaire (~50 000 morts à Gaza, famine documentée), cette guerre teste la crédibilité du droit international (procès CIJ, plaintes CPI), polarise les opinions occidentales et du Sud global, et reconfigure le Moyen-Orient. Elle bloque la normalisation arabe d'Israël et alimente partout les récits anti-impérialistes — y compris au Burkina Faso.\n\nIMPACT POUR L'AES — Modérée (impact diplomatique et symbolique) : Le BF n'est pas acteur direct mais la cause palestinienne structure la rhétorique anti-occidentale du régime et l'imaginaire panafricain. : Pas d'impact sécuritaire direct. Mais radicalisation idéologique via réseaux numériques mobilise jihadistes sahéli…\n\nSCÉNARIOS —\n• Tendanciel — guerre prolongée à intensité variable (45%) : Pas de cessez-le-feu durable. Opérations IDF récurrentes Gaza et Cisjordanie. Tirs sporadiques Sud-Liban. Hamas se reconstitue lentement. Reconstruction quasi-nulle. Crise humanitaire chronique.\n• Recomposition — plan régional Trump/Saoudien (25%) : Force internationale arabe (saoudienne, EAU, Égypte) à Gaza. Réforme Autorité palestinienne. Reconstruction financée Golfe. Normalisation saoudienne phase 1. Cisjordanie en attente.\n\nÀ SURVEILLER — Le plan régional Trump-Saoudien (force internationale arabe à Gaza ?). ; L'évolution Cisjordanie : risque de 3e Intifada. ; La survie de la coalition Netanyahou (otages, procès, élections).",
      "prospective": "12-24 mois : probable statu quo dégradé, occupation militaire permanente Gaza, raids Cisjordanie.",
      "confiance": "eleve",
      "proseIA": null
    },
    "c_sdn": {
      "id": "c_sdn",
      "name": "Soudan",
      "volume": 31,
      "themesDominants": [
        "Politique interne & gouvernance",
        "Maritime & océanique",
        "Économie & ressources"
      ],
      "faits": [
        {
          "titre": "Bobo-Dioulasso : Trois corps sans vie déposés à la morgue du CHU Souro Sanou dont un bébé de 3 semaines",
          "source": "Net Afrique (BF)",
          "cote": "F2",
          "lien": "https://netafrique.net/bobo-dioulasso-trois-corps-sans-vie-deposes-a-la-morgue-du-chu-souro-sanou-dont-un-bebe-de-3-semaines/",
          "theme": "P"
        },
        {
          "titre": "Pakistan urges US, Iran to 'end violence', resume technical-level talks",
          "source": "Dawn (Pakistan)",
          "cote": "F1",
          "lien": "https://www.dawn.com/news/2015882/pakistan-urges-us-iran-to-end-violence-resume-technical-level-talks",
          "theme": "M"
        },
        {
          "titre": "Stock market experts optimistic on H2’26 but warn investors",
          "source": "Vanguard (Nigeria)",
          "cote": "F2",
          "lien": "https://www.vanguardngr.com/2026/07/stock-market-experts-optimistic-on-h226-but-warn-investors/",
          "theme": "E"
        },
        {
          "titre": "EU: Tunisia Migration Deal Worsening Human Rights Violations",
          "source": "Human Rights Watch",
          "cote": "F2",
          "lien": "https://www.hrw.org/news/2026/07/16/eu-tunisia-migration-deal-worsening-human-rights-violations",
          "theme": "D"
        },
        {
          "titre": "Ukraine: Russian-Run Schools Violate Children’s Rights",
          "source": "Human Rights Watch",
          "cote": "F2",
          "lien": "https://www.hrw.org/news/2026/07/16/ukraine-russian-run-schools-violate-childrens-rights",
          "theme": "I"
        },
        {
          "titre": "PMA issues red alert over 651,000 zero-dose children",
          "source": "Dawn (Pakistan)",
          "cote": "A3",
          "lien": "https://www.dawn.com/news/2015789/pma-issues-red-alert-over-651000-zero-dose-children",
          "theme": null
        }
      ],
      "enjeu": "Le Soudan est trop grand et trop divers pour qu'une victoire militaire d'un camp permette de gouverner. Toute issue militaire produira un État défaillant. Mais aucune négociation ne marche.",
      "consequencesAES": "Modérée (effet rebond Sahel) : Le BF subit la déstabilisation régionale et la concurrence pour l'attention humanitaire. : Aucun impact sécuritaire direct (distance géographique Soudan-BF ~3 500 km). · Possible diffusion modèle RSF/Janjaweed vers groupes sahéliens ? Pas documenté. · Réfugiés soudanai…",
      "lectureStructuree": "SITUATION (live) — 31 dépêches sur la période, dominante : Politique interne & gouvernance, Maritime & océanique, Économie & ressources.\nFaits saillants : « Bobo-Dioulasso : Trois corps sans vie déposés à la morgue du CHU Souro Sanou dont un bébé de 3 semaines » (Net Afrique (BF), cote F2) ; « Pakistan urges US, Iran to 'end violence', resume technical-level talks » (Dawn (Pakistan), cote F1) ; « Stock market experts optimistic on H2’26 but warn investors » (Vanguard (Nigeria), cote F2).\n\nENJEU CENTRAL — Le Soudan est trop grand et trop divers pour qu'une victoire militaire d'un camp permette de gouverner. Toute issue militaire produira un État défaillant. Mais aucune négociation ne marche.\n\nPOURQUOI — C'est la guerre la plus meurtrière du moment (~150 000 morts, 10 millions de déplacés, famine déclarée IPC 5) et pourtant la moins couverte. Elle illustre l'effondrement total d'un État de 48 millions d'habitants, alimenté par des sponsors régionaux (EAU vs Égypte/Arabie). Sa persistance déstabilise la mer Rouge, le Tchad, le Sud-Soudan, et révèle la faillite des médiations africaines et arabes.\n\nIMPACT POUR L'AES — Modérée (effet rebond Sahel) : Le BF subit la déstabilisation régionale et la concurrence pour l'attention humanitaire. : Aucun impact sécuritaire direct (distance géographique Soudan-BF ~3 500 km). · Possible diffusion modèle RSF/Janjaweed vers groupes sahéliens ? Pas documenté. · Réfugiés soudanai…\n\nSCÉNARIOS —\n• Tendanciel — partition de fait (50%) : SAF tient Nord/Centre/Est avec capitale Khartoum reprise. RSF tient Darfour/Kordofan-Sud. Pas d'accord politique. Économie effondrée. Crise humanitaire chronique. Pas de service public.\n• Recomposition — médiation Trump-Saoudite (20%) : Pression US (sanctions, déclaration génocide) force EAU à lâcher RSF. Médiation Saoudite-Égypte. Cessez-le-feu, cantonnement RSF. Transition militaire-civile négociée.\n\nÀ SURVEILLER — L'évolution du soutien émirien aux RSF face aux pressions US (génocide reconnu jan. 2025). ; Le sort d'El Fasher au Darfour (massacres documentés). ; La possibilité d'une base navale russe à Port-Soudan (recomposition mer Rouge).",
      "prospective": "12-24 mois : partition de fait probable. SAF contrôle Khartoum/Nord/Est, RSF contrôle Darfour/Kordofan-Sud.",
      "confiance": "eleve",
      "proseIA": null
    },
    "c_tai": {
      "id": "c_tai",
      "name": "Taïwan",
      "volume": 71,
      "themesDominants": [
        "Maritime & océanique",
        "Économie & ressources",
        "Sécurité & défense"
      ],
      "faits": [
        {
          "titre": "Iran warns Strait of Hormuz is a 'red line' and will resist until the end",
          "source": "Al-Monitor",
          "cote": "F2",
          "lien": "https://www.al-monitor.com/originals/2026/07/iran-warns-strait-hormuz-red-line-and-will-resist-until-end",
          "theme": "M"
        },
        {
          "titre": "Fewer vessels travel through Hormuz after US resumes blockade",
          "source": "Al-Monitor",
          "cote": "F2",
          "lien": "https://www.al-monitor.com/originals/2026/07/fewer-vessels-travel-through-hormuz-after-us-resumes-blockade",
          "theme": "M"
        },
        {
          "titre": "Pakistan urges US, Iran to 'end violence', resume technical-level talks",
          "source": "Dawn (Pakistan)",
          "cote": "F1",
          "lien": "https://www.dawn.com/news/2015882/pakistan-urges-us-iran-to-end-violence-resume-technical-level-talks",
          "theme": "M"
        },
        {
          "titre": "Oil price reverses gains, falls 0.8% despite escalating US-Iran hostilities",
          "source": "Vanguard (Nigeria)",
          "cote": "F2",
          "lien": "https://www.vanguardngr.com/2026/07/oil-price-reverses-gains-falls-0-8-despite-escalating-us-iran-hostilities/",
          "theme": "E"
        },
        {
          "titre": "Depuis 2022 et le début de la guerre en Ukraine, l’électrification de l’Union n’a que très peu évolué",
          "source": "Le Grand Continent",
          "cote": "A2",
          "lien": "https://legrandcontinent.eu/fr/2026/07/16/depuis-2022-et-le-debut-de-la-guerre-en-ukraine-lelectrification-de-lunion-na-que-tres-peu-evolue/",
          "theme": "E"
        },
        {
          "titre": "Le Pentagone s’en prend aux puissances moyennes",
          "source": "Le Grand Continent",
          "cote": "A2",
          "lien": "https://legrandcontinent.eu/fr/2026/07/16/le-pentagone-sen-prend-aux-puissances-moyennes/",
          "theme": "S"
        }
      ],
      "enjeu": "TSMC fait de Taïwan un nœud systémique de l'économie mondiale. Cela renforce la dissuasion (« bouclier de silicium ») mais aussi l'enjeu, donc la tentation chinoise de neutraliser cet avantage par la force.",
      "consequencesAES": "Élevée (impact macro mondial) : Une crise Taïwan = choc économique global qui frapperait le BF de plein fouet via les puces, l'inflation et le dollar. : Impact sécuritaire direct nul (Asie Pacifique). · Mais : crise Taïwan distrait attention US/UE → désengagement d'autres théâtres (Sahel, Sahel orie…",
      "lectureStructuree": "SITUATION (live) — 71 dépêches sur la période, dominante : Maritime & océanique, Économie & ressources, Sécurité & défense.\nFaits saillants : « Iran warns Strait of Hormuz is a 'red line' and will resist until the end » (Al-Monitor, cote F2) ; « Fewer vessels travel through Hormuz after US resumes blockade » (Al-Monitor, cote F2) ; « Pakistan urges US, Iran to 'end violence', resume technical-level talks » (Dawn (Pakistan), cote F1).\n\nENJEU CENTRAL — TSMC fait de Taïwan un nœud systémique de l'économie mondiale. Cela renforce la dissuasion (« bouclier de silicium ») mais aussi l'enjeu, donc la tentation chinoise de neutraliser cet avantage par la force.\n\nPOURQUOI — Une crise Taïwan ne serait pas régionale : ce serait l'équivalent de COVID + crise de 2008 combinés. Sans TSMC, l'IA, les smartphones, les voitures, la défense s'arrêtent en quelques mois. C'est aussi le test ultime de la primauté américaine en Pacifique : si Pékin gagne, la première chaîne d'îles tombe et l'ordre indo-pacifique bascule pour 50 ans.\n\nIMPACT POUR L'AES — Élevée (impact macro mondial) : Une crise Taïwan = choc économique global qui frapperait le BF de plein fouet via les puces, l'inflation et le dollar. : Impact sécuritaire direct nul (Asie Pacifique). · Mais : crise Taïwan distrait attention US/UE → désengagement d'autres théâtres (Sahel, Sahel orie…\n\nSCÉNARIOS —\n• Tendanciel — pression militaire constante, pas d'invasion (50%) : Pékin maintient pression militaire/économique/diplomatique. Taïwan se réarme. Économie mondiale absorbe coût continu de la « zone grise ». USA maintiennent ambiguïté.\n• Rupture — crise majeure non-cinétique (25%) : Blocus partiel ou « quarantaine » sanitaire/douanière. Test résolution US/alliés. Crise économique aiguë. Pas de guerre directe mais redéfinition règles.\n\nÀ SURVEILLER — Les exercices PLA majeurs (encerclement, blocus simulés). ; La position de Trump sur l'engagement militaire en cas d'invasion. ; Les avancées de TSMC en Arizona (relocalisation 100 Mds USD).",
      "prospective": "12-36 mois : pression militaire constante mais pas d'invasion immédiate. Risque crise non-cinétique (blocus, quarantaine).",
      "confiance": "eleve",
      "proseIA": null
    },
    "c_cod": {
      "id": "c_cod",
      "name": "RDC-Est",
      "volume": 26,
      "themesDominants": [
        "Politique interne & gouvernance",
        "Diplomatie & alliances",
        "Économie & ressources"
      ],
      "faits": [
        {
          "titre": "Tchad: le Président annonce la suppression des visas d’entrée sur le territoire pour tous les Africains dès le 1er janvier 2027",
          "source": "AIB — Agence Information BF",
          "cote": "C2",
          "lien": "https://www.aib.media/tchad-le-president-annonce-la-suppression-des-visas-dentree-sur-le-territoire-pour-tous-les-africains-des-le-1er-janvier-2027/",
          "theme": "P"
        },
        {
          "titre": "Un Conseil consultatif international mis en place pour pousser le processus de reconnaissance des atrocités perpétrées en RDC",
          "source": "ActualitéCD (RDC)",
          "cote": "F2",
          "lien": "https://actualite.cd/2026/07/16/un-conseil-consultatif-international-mis-en-place-pour-pousser-le-processus-de",
          "theme": "D"
        },
        {
          "titre": "Retrait des troupes rwandaises de l’Est de la RDC : l’ultimatum américain ignoré ?",
          "source": "France 24",
          "cote": "A1",
          "lien": "https://www.france24.com/fr/%C3%A9missions/journal-de-l-afrique/20260715-retrait-des-troupes-rwandaises-de-l-est-de-la-rdc-l-ultimatum-am%C3%A9ricain-ignor%C3%A9",
          "theme": null
        },
        {
          "titre": "Conférence internationale flex2026: La transformation des systèmes éducatifs africains en discussion à Lilongwé",
          "source": "Le Soleil (Sénégal)",
          "cote": "F2",
          "lien": "https://lesoleil.sn/actualites/education/conference-internationale-flex2026-la-transformation-des-systemes-educatifs-africains-en-discussion-a-lilongwe/",
          "theme": null
        },
        {
          "titre": "Meilleurs joueurs du Mondial 2026 : Ismaïla Sarr, seul Lion dans le Top 50",
          "source": "Le Soleil (Sénégal)",
          "cote": "F2",
          "lien": "https://lesoleil.sn/actualites/sports/mondial-2026/meilleurs-joueurs-du-mondial-2026-ismaila-sarr-seul-lion-dans-le-top-50/",
          "theme": "E"
        },
        {
          "titre": "Assemblée nationale : la nouvelle loi de programmation militaire 2027-2030 mise sur la professionnalisation des FARDC",
          "source": "Radio Okapi (RDC)",
          "cote": "F2",
          "lien": "https://www.radiookapi.net/2026/07/16/actualite/politique/assemblee-nationale-la-nouvelle-loi-de-programmation-militaire-2027",
          "theme": "S"
        }
      ],
      "enjeu": "La RDC ne peut pas reconquérir le Kivu militairement seule. Le Rwanda ne peut pas annexer ouvertement sans crise diplomatique majeure. C'est un statu quo violent durable.",
      "consequencesAES": "Modérée (effet ressources critiques) : Le BF subit indirectement la crise du coltan et des minerais critiques, et observe avec intérêt le modèle d'État défaillant. : Pas d'impact sécuritaire direct (RDC à 2 500 km). · Mais : effet de précédent. Captation territoriale par voisin (Rwanda) sans réactio…",
      "lectureStructuree": "SITUATION (live) — 26 dépêches sur la période, dominante : Politique interne & gouvernance, Diplomatie & alliances, Économie & ressources.\nFaits saillants : « Tchad: le Président annonce la suppression des visas d’entrée sur le territoire pour tous les Africains dès le 1er janvier 2027 » (AIB — Agence Information BF, cote C2) ; « Un Conseil consultatif international mis en place pour pousser le processus de reconnaissance des atrocités perpétrées en RDC » (ActualitéCD (RDC), cote F2) ; « Retrait des troupes rwandaises de l’Est de la RDC : l’ultimatum américain ignoré ? » (France 24, cote A1).\n\nENJEU CENTRAL — La RDC ne peut pas reconquérir le Kivu militairement seule. Le Rwanda ne peut pas annexer ouvertement sans crise diplomatique majeure. C'est un statu quo violent durable.\n\nPOURQUOI — C'est le théâtre de la longue guerre des Grands Lacs (~6 millions de morts cumulés depuis 1996). Au-delà de la dimension humanitaire (~7 millions de déplacés), le coltan congolais (70% production mondiale) est indispensable à toute l'industrie tech mondiale. La crise illustre aussi la captation des ressources africaines par procuration et l'échec total des médiations EAC, SADC, UA face à un agresseur — le Rwanda — protégé par sa mémoire post-génocide.\n\nIMPACT POUR L'AES — Modérée (effet ressources critiques) : Le BF subit indirectement la crise du coltan et des minerais critiques, et observe avec intérêt le modèle d'État défaillant. : Pas d'impact sécuritaire direct (RDC à 2 500 km). · Mais : effet de précédent. Captation territoriale par voisin (Rwanda) sans réactio…\n\nSCÉNARIOS —\n• Tendanciel — partition de fait (45%) : Kivu sous contrôle M23/Rwanda. Kinshasa garde reste mais perd autorité Est. Économie de prédation continue. ~7-10 M déplacés. Pas d'accord politique.\n• Escalade — guerre régionale (Burundi-Rwanda) (25%) : Engagement direct Burundi-Rwanda autour Sud-Kivu. Risque Ouganda en bascule. Lac Tanganyika nœud. ~5 M réfugiés supplémentaires. Implication EAC.\n\nÀ SURVEILLER — Les mouvements vers Bukavu et au-delà (Sud-Kivu vers Burundi). ; Les sanctions Trump sur le Rwanda (déclaration soutien M23 ?). ; Le sort de la MONUSCO (retrait achevé) et l'éventuelle nouvelle force africaine.",
      "prospective": "12-36 mois : partition de fait du Kivu. Kinshasa contrôle le reste mais perd autorité dans l'Est.",
      "confiance": "eleve",
      "proseIA": null
    },
    "c_yem": {
      "id": "c_yem",
      "name": "Mer Rouge",
      "volume": 39,
      "themesDominants": [
        "Maritime & océanique",
        "Économie & ressources",
        "Sécurité & défense"
      ],
      "faits": [
        {
          "titre": "Iran warns Strait of Hormuz is a 'red line' and will resist until the end",
          "source": "Al-Monitor",
          "cote": "F2",
          "lien": "https://www.al-monitor.com/originals/2026/07/iran-warns-strait-hormuz-red-line-and-will-resist-until-end",
          "theme": "M"
        },
        {
          "titre": "Fewer vessels travel through Hormuz after US resumes blockade",
          "source": "Al-Monitor",
          "cote": "F2",
          "lien": "https://www.al-monitor.com/originals/2026/07/fewer-vessels-travel-through-hormuz-after-us-resumes-blockade",
          "theme": "M"
        },
        {
          "titre": "Pakistan urges US, Iran to 'end violence', resume technical-level talks",
          "source": "Dawn (Pakistan)",
          "cote": "F1",
          "lien": "https://www.dawn.com/news/2015882/pakistan-urges-us-iran-to-end-violence-resume-technical-level-talks",
          "theme": "M"
        },
        {
          "titre": "Stock market experts optimistic on H2’26 but warn investors",
          "source": "Vanguard (Nigeria)",
          "cote": "F2",
          "lien": "https://www.vanguardngr.com/2026/07/stock-market-experts-optimistic-on-h226-but-warn-investors/",
          "theme": "E"
        },
        {
          "titre": "Oil price reverses gains, falls 0.8% despite escalating US-Iran hostilities",
          "source": "Vanguard (Nigeria)",
          "cote": "F2",
          "lien": "https://www.vanguardngr.com/2026/07/oil-price-reverses-gains-falls-0-8-despite-escalating-us-iran-hostilities/",
          "theme": "E"
        },
        {
          "titre": "Le Pentagone s’en prend aux puissances moyennes",
          "source": "Le Grand Continent",
          "cote": "A2",
          "lien": "https://legrandcontinent.eu/fr/2026/07/16/le-pentagone-sen-prend-aux-puissances-moyennes/",
          "theme": "S"
        }
      ],
      "enjeu": "Un acteur asymétrique armé de drones à 30 000 USD peut paralyser le commerce maritime mondial pendant des mois. C'est une révolution de l'asymétrie qui change toutes les doctrines navales.",
      "consequencesAES": "",
      "lectureStructuree": "SITUATION (live) — 39 dépêches sur la période, dominante : Maritime & océanique, Économie & ressources, Sécurité & défense.\nFaits saillants : « Iran warns Strait of Hormuz is a 'red line' and will resist until the end » (Al-Monitor, cote F2) ; « Fewer vessels travel through Hormuz after US resumes blockade » (Al-Monitor, cote F2) ; « Pakistan urges US, Iran to 'end violence', resume technical-level talks » (Dawn (Pakistan), cote F1).\n\nENJEU CENTRAL — Un acteur asymétrique armé de drones à 30 000 USD peut paralyser le commerce maritime mondial pendant des mois. C'est une révolution de l'asymétrie qui change toutes les doctrines navales.\n\nPOURQUOI — Bab el-Mandeb verrouille le passage entre Suez et l'océan Indien. Sa fermeture force les navires à contourner par le cap de Bonne-Espérance (+10-14 jours, +30% coût). Les frappes US-UK ne font pas reculer les Houthis, qui sortent renforcés (popularité gonflée, légitimité régionale, leçon utile pour tout acteur asymétrique). Cela impacte directement le commerce du Burkina Faso (importations Asie) et tous les pays enclavés du Sahel.\n\nÀ SURVEILLER — Le maintien ou la levée du blocus mer Rouge. ; Les négociations saoudo-houthies (gel possible ?). ; Le transfert de technologies iraniennes après l'effondrement de l'arc chiite.",
      "prospective": "6-18 mois : maintien du harcèlement maritime probable, sauf accord régional global.",
      "confiance": "eleve",
      "proseIA": null
    },
    "c_kor": {
      "id": "c_kor",
      "name": "Corée",
      "volume": 15,
      "themesDominants": [
        "Sécurité & défense",
        "Économie & ressources",
        "Climat & environnement"
      ],
      "faits": [
        {
          "titre": "Burkina Faso : Les Forces combattantes consolident leurs avancées territoriales en nettoyant plusieurs repaires terroristes",
          "source": "Net Afrique (BF)",
          "cote": "F1",
          "lien": "https://netafrique.net/burkina-faso-les-forces-combattantes-consolident-leurs-avancees-territoriales-en-nettoyant-plusieurs-repaires-terroristes/",
          "theme": "S"
        },
        {
          "titre": "Les nouvelles du front: les Forces combattantes consolident leurs avancées territoriales en nettoyant plusieurs repaires terroristes",
          "source": "Sidwaya",
          "cote": "C1",
          "lien": "https://www.sidwaya.info/les-forces-combattantes-consolident-leurs-avancees-territoriales-en-nettoyant-plusieurs-repaires-terroristes/",
          "theme": "S"
        },
        {
          "titre": "Stock market experts optimistic on H2’26 but warn investors",
          "source": "Vanguard (Nigeria)",
          "cote": "F2",
          "lien": "https://www.vanguardngr.com/2026/07/stock-market-experts-optimistic-on-h226-but-warn-investors/",
          "theme": "E"
        },
        {
          "titre": "Frontline communities face longer wait for funds",
          "source": "Dawn (Pakistan)",
          "cote": "F2",
          "lien": "https://www.dawn.com/news/2015776/frontline-communities-face-longer-wait-for-funds",
          "theme": "C"
        },
        {
          "titre": "Takanomics vs Abenomics: the $2.3tn prizefight",
          "source": "Financial Times World",
          "cote": "B2",
          "lien": "https://www.ft.com/content/15f15092-3b14-4ba7-be3a-d3cdf70ed670",
          "theme": null
        },
        {
          "titre": "Tarkwa: Court jails 19-year-old five years for stealing nurse’s iPhone, cash",
          "source": "MyJoyOnline (Ghana)",
          "cote": "F2",
          "lien": "https://www.myjoyonline.com/tarkwa-court-jails-19-year-old-five-years-for-stealing-nurses-iphone-cash/",
          "theme": null
        }
      ],
      "enjeu": "L'axe Russie-Corée du Nord brise les sanctions internationales et démontre qu'un État-paria peut sortir de l'isolement en s'alignant sur une grande puissance révisionniste.",
      "consequencesAES": "",
      "lectureStructuree": "SITUATION (live) — 15 dépêches sur la période, dominante : Sécurité & défense, Économie & ressources, Climat & environnement.\nFaits saillants : « Burkina Faso : Les Forces combattantes consolident leurs avancées territoriales en nettoyant plusieurs repaires terroristes » (Net Afrique (BF), cote F1) ; « Les nouvelles du front: les Forces combattantes consolident leurs avancées territoriales en nettoyant plusieurs repaires terroristes » (Sidwaya, cote C1) ; « Stock market experts optimistic on H2’26 but warn investors » (Vanguard (Nigeria), cote F2).\n\nENJEU CENTRAL — L'axe Russie-Corée du Nord brise les sanctions internationales et démontre qu'un État-paria peut sortir de l'isolement en s'alignant sur une grande puissance révisionniste.\n\nPOURQUOI — Le pacte Russie-Corée du Nord (juin 2024) est la première véritable alliance entre une puissance nucléaire et un État-paria depuis longtemps. ~12 000 soldats nord-coréens en Koursk = première projection terrestre de Pyongyang depuis 1953. En échange, Moscou transfère des technologies qui font sauter les verrous sur le programme nord-coréen, augmentant directement la menace pour le Japon, la Corée du Sud et les États-Unis.\n\nÀ SURVEILLER — Les tirs balistiques de nouvelle génération. ; La diplomatie Trump-Kim (sommet possible ?). ; Le retour des troupes nord-coréennes de Russie avec expérience combat.",
      "prospective": "12-24 mois : poursuite du rapprochement RU-PRK, renforcement programmes, peut-être test nucléaire.",
      "confiance": "eleve",
      "proseIA": null
    },
    "c_syr": {
      "id": "c_syr",
      "name": "Syrie",
      "volume": 37,
      "themesDominants": [
        "Diplomatie & alliances",
        "Information & influence",
        "Politique interne & gouvernance"
      ],
      "faits": [
        {
          "titre": "Expulsion des diplomates de l’UE : en toute souveraineté !",
          "source": "Sidwaya",
          "cote": "C2",
          "lien": "https://www.sidwaya.info/expulsion-des-diplomates-de-lue-en-toute-souverainete/",
          "theme": "D"
        },
        {
          "titre": "Air France, Brussels Airlines, Air Algérie… La réconciliation entre Bamako et Alger, une aubaine pour l’aérien ?",
          "source": "Jeune Afrique",
          "cote": "B2",
          "lien": "https://www.jeuneafrique.com/1818435/economie-entreprises/air-france-brussels-airlines-air-algerie-la-reconciliation-entre-bamako-et-alger-une-aubaine-pour-laerien/",
          "theme": "D"
        },
        {
          "titre": "EU: Tunisia Migration Deal Worsening Human Rights Violations",
          "source": "Human Rights Watch",
          "cote": "F2",
          "lien": "https://www.hrw.org/news/2026/07/16/eu-tunisia-migration-deal-worsening-human-rights-violations",
          "theme": "D"
        },
        {
          "titre": "Ukraine: Russian-Run Schools Violate Children’s Rights",
          "source": "Human Rights Watch",
          "cote": "F2",
          "lien": "https://www.hrw.org/news/2026/07/16/ukraine-russian-run-schools-violate-childrens-rights",
          "theme": "I"
        },
        {
          "titre": "Xénophobie au Sénégal: le président du GOHA International lance un appel urgent pour protéger les Guinéens",
          "source": "Mediaguinee",
          "cote": "F2",
          "lien": "https://mediaguinee.com/2026/07/xenophobie-au-senegal-le-president-du-goha-international-lance-un-appel-urgent-pour-proteger-les-guineens/",
          "theme": "P"
        },
        {
          "titre": "Syrian foils attempt to smuggle weapons, missiles to Hezbollah",
          "source": "Anadolu Agency (Turquie)",
          "cote": "A2",
          "lien": "https://www.aa.com.tr/en/middle-east/syrian-foils-attempt-to-smuggle-weapons-missiles-to-hezbollah/4000093",
          "theme": "L"
        }
      ],
      "enjeu": "La transition syrienne peut reconstruire un État viable (rare) ou se fragmenter en libanisation (probable). La gestion de la question kurde et le retour des réfugiés sont les vraies épreuves.",
      "consequencesAES": "",
      "lectureStructuree": "SITUATION (live) — 37 dépêches sur la période, dominante : Diplomatie & alliances, Information & influence, Politique interne & gouvernance.\nFaits saillants : « Expulsion des diplomates de l’UE : en toute souveraineté ! » (Sidwaya, cote C2) ; « Air France, Brussels Airlines, Air Algérie… La réconciliation entre Bamako et Alger, une aubaine pour l’aérien ? » (Jeune Afrique, cote B2) ; « EU: Tunisia Migration Deal Worsening Human Rights Violations » (Human Rights Watch, cote F2).\n\nENJEU CENTRAL — La transition syrienne peut reconstruire un État viable (rare) ou se fragmenter en libanisation (probable). La gestion de la question kurde et le retour des réfugiés sont les vraies épreuves.\n\nPOURQUOI — La Syrie était le pilier oriental de l'arc chiite iranien et de la projection russe en Méditerranée (base Tartous). Sa chute reconfigure tout le Levant : Iran isolé, Russie affaiblie, Hezbollah privé de corridor logistique, Turquie en position de force. Mais HTS reste suspect (passé jihadiste), la question kurde non résolue, Israël a détruit 80% des capacités militaires syriennes en 48h post-Assad.\n\nÀ SURVEILLER — Les négociations HTS-SDF sur l'avenir des Kurdes. ; La levée ou non des sanctions occidentales sur le nouveau régime. ; Le retour des réfugiés syriens depuis Turquie/Liban (~6 millions).",
      "prospective": "6-12 mois : stabilisation fragile ou fragmentation. Décision cruciale sur Kurdes.",
      "confiance": "eleve",
      "proseIA": null
    }
  },
  "syntheseExecutive": "Sur la période, 800 dépêches ont été classées et cotées. Priorité géographique : 1. Sahel & AO franco. (83 signaux, tendance stable). Ruptures repérées : Iran warns Strait of Hormuz is a 'red line' and will resist until the end ; U.S. airstrikes hit northern Iran as it disables ship trying to run blockade. Signaux faibles émergents à surveiller : 18. Amérique du Sud · Diplomatie & alliances ; 12. Asie du Sud · Maritime & océanique ; 3. Afrique centrale · Information & influence.\n\nSujets chauds de la période :\n• Iran-Israël (116 signaux) — La question nucléaire iranienne et la survie du régime des Pasdaran détermineront la stabilité régionale pour 20 ans.\n• Sahel/AES (91 signaux) — Inventer un modèle politique africain qui combine souveraineté affichée et efficacité sécuritaire — sans y être encore parvenu.\n• Taïwan (71 signaux) — TSMC fait de Taïwan un nœud systémique de l'économie mondiale. Cela renforce la dissuasion (« bouclier de silicium ») mais aussi l'enjeu, donc la tentation chinoise de neutraliser cet avantage par la force.",
  "llmUsed": false,
  "achSuggestions": [
    {
      "conflictId": "c_iran_il",
      "name": "Iran-Israël",
      "hypotheses": [
        "Iran-Israël : escalade / aggravation a 3-6 mois",
        "Iran-Israël : statu quo instable",
        "Iran-Israël : desescalade / reglement partiel"
      ],
      "evidence": [
        "Appel solennel à l’engagement des Patriotes pour la République",
        "Iran warns Strait of Hormuz is a 'red line' and will resist until the end",
        "U.S. airstrikes hit northern Iran as it disables ship trying to run blockade",
        "Fewer vessels travel through Hormuz after US resumes blockade",
        "Pakistan urges US, Iran to 'end violence', resume technical-level talks"
      ]
    },
    {
      "conflictId": "c_aes",
      "name": "Sahel/AES",
      "hypotheses": [
        "Sahel/AES : escalade / aggravation a 3-6 mois",
        "Sahel/AES : statu quo instable",
        "Sahel/AES : desescalade / reglement partiel"
      ],
      "evidence": [
        "Burkina: le chef de la diplomatie burkinabè échange avec le président de la Commission de l’UA sur la coopération bilatérale",
        "Coordination air-sol : De Yensé à Diabatou, l’armée burkinabè met en déroute les groupes armés au Nord et à l’Est",
        "EBOMAF-GABON : 485 km de routes pour construire l’avenir",
        "Oudalan: la commune de Gorom-Gorom inaugure le « Rond-point de la Paix » à l’effigie d’un dromadaire pour valoriser son identité culturelle",
        "Poni/Tourisme éducatif: des élèves de l’école annexe de Gaoua à la découverte du patrimoine historique de Batié"
      ]
    },
    {
      "conflictId": "c_tai",
      "name": "Taïwan",
      "hypotheses": [
        "Taïwan : escalade / aggravation a 3-6 mois",
        "Taïwan : statu quo instable",
        "Taïwan : desescalade / reglement partiel"
      ],
      "evidence": [
        "Iran warns Strait of Hormuz is a 'red line' and will resist until the end",
        "Fewer vessels travel through Hormuz after US resumes blockade",
        "Pakistan urges US, Iran to 'end violence', resume technical-level talks",
        "Oil price reverses gains, falls 0.8% despite escalating US-Iran hostilities",
        "Depuis 2022 et le début de la guerre en Ukraine, l’électrification de l’Union n’a que très peu évolué"
      ]
    }
  ],
  "agentLog": [
    {
      "at": "2026-07-16T09:28:20.585Z",
      "agent": "Agent Analyste",
      "message": "Demarrage (IA: non, mode structure)"
    },
    {
      "at": "2026-07-16T09:28:20.609Z",
      "agent": "Agent Analyste",
      "message": "10 conflits charges"
    },
    {
      "at": "2026-07-16T09:28:20.610Z",
      "agent": "Agent Analyste",
      "message": "800 articles dans la fenetre (168 h)"
    },
    {
      "at": "2026-07-16T09:28:20.616Z",
      "agent": "Agent Analyste",
      "message": "Detection: 9 tendances, 8 signaux faibles, 8 ruptures, 0 recompositions"
    },
    {
      "at": "2026-07-16T09:28:20.695Z",
      "agent": "Agent Analyste",
      "message": "10 conflits analyses, 3 suggestions ACH"
    },
    {
      "at": "2026-07-16T09:28:20.695Z",
      "agent": "Agent Analyste",
      "message": "Productions: 3 notes zone, 3 prospectives, 4 etudes"
    }
  ]
}