{
  "generatedAt": "2026-06-09T10:37:42.811Z",
  "stats": {
    "analysed": 800,
    "windowHours": 168,
    "sources": 73
  },
  "findings": {
    "tendancesLourdes": [
      {
        "axe": "thematique",
        "cle": "P",
        "libelle": "Politique interne & gouvernance",
        "volume": 100,
        "base": 118.6,
        "direction": "stable"
      },
      {
        "axe": "thematique",
        "cle": "E",
        "libelle": "Économie & ressources",
        "volume": 82,
        "base": 86.9,
        "direction": "stable"
      },
      {
        "axe": "thematique",
        "cle": "S",
        "libelle": "Sécurité & défense",
        "volume": 59,
        "base": 62.2,
        "direction": "stable"
      },
      {
        "axe": "thematique",
        "cle": "D",
        "libelle": "Diplomatie & alliances",
        "volume": 55,
        "base": 51.6,
        "direction": "stable"
      },
      {
        "axe": "thematique",
        "cle": "J",
        "libelle": "Justice & droit international",
        "volume": 25,
        "base": 24,
        "direction": "stable"
      },
      {
        "axe": "zone",
        "cle": 1,
        "libelle": "1. Sahel & AO franco.",
        "volume": 74,
        "base": 84.4,
        "direction": "stable"
      },
      {
        "axe": "zone",
        "cle": 2,
        "libelle": "2. AO anglo. & côtière",
        "volume": 61,
        "base": 54.9,
        "direction": "stable"
      },
      {
        "axe": "zone",
        "cle": 7,
        "libelle": "7. Maghreb & Afr. Nord",
        "volume": 24,
        "base": 28.6,
        "direction": "stable"
      },
      {
        "axe": "zone",
        "cle": 4,
        "libelle": "4. Grands Lacs",
        "volume": 16,
        "base": 13.5,
        "direction": "stable"
      }
    ],
    "signauxFaibles": [
      {
        "zone": "13. Asie du Sud-Est",
        "thematique": "Diplomatie & alliances",
        "code": "D",
        "volume": 2,
        "exemple": "As Putin courts Southeast Asia, does ‘Russia need Asean more’?"
      },
      {
        "zone": "3. Afrique centrale",
        "thematique": "Maritime & océanique",
        "code": "M",
        "volume": 1,
        "exemple": "Dénoncé par Libreville, l’accord de pêche avec l’UE pourrait renaître sous une nouvelle forme"
      },
      {
        "zone": "11. Asie centrale",
        "thematique": "Sécurité & défense",
        "code": "S",
        "volume": 1,
        "exemple": "India's key objectives in Afghanistan solely driven by singular goal of destabilising Pakistan, envoy tells UNSC"
      },
      {
        "zone": "13. Asie du Sud-Est",
        "thematique": "Maritime & océanique",
        "code": "M",
        "volume": 1,
        "exemple": "Is that a Chinese antenna at Scarborough Shoal? The Philippines thinks so"
      },
      {
        "zone": "6. Afrique australe",
        "thematique": "Climat & environnement",
        "code": "C",
        "volume": 1,
        "exemple": "Africa struggles to turn forest and biodiversity policies into action, experts say at regional webinar"
      },
      {
        "zone": "9. Europe occidentale",
        "thematique": "Technologie & cyber",
        "code": "T",
        "volume": 1,
        "exemple": "Tchap, la messagerie sécurisée de l’État français, victime d’une cyberattaque"
      },
      {
        "zone": "12. Asie du Sud",
        "thematique": "Climat & environnement",
        "code": "C",
        "volume": 1,
        "exemple": "Vagues de chaleur à répétition : l'Inde suffoque et souffre des pénuries d'eau"
      },
      {
        "zone": "4. Grands Lacs",
        "thematique": "Climat & environnement",
        "code": "C",
        "volume": 1,
        "exemple": "«Le lac a détruit nos maisons et nos vies»: dans l’est de la RDC, Kalemie face à la montée du Tanganyika"
      }
    ],
    "ruptures": [
      {
        "type": "evenement",
        "zone": "1. Sahel & AO franco.",
        "thematique": "Humanitaire & social",
        "titre": "Ouagadougou : L’effondrement de la dalle d’un bâtiment R+1 fait des victimes",
        "source": "Minute BF",
        "cote": "F1",
        "lien": "https://www.minute.bf/ouagadougou-leffondrement-de-la-dalle-dun-batiment-r1-fait-des-victimes/"
      },
      {
        "type": "evenement",
        "zone": "8. Moyen-Orient",
        "thematique": "Sécurité & défense",
        "titre": "Guerre au Moyen-Orient : les négociateurs s’activent malgré l’escalade militaire",
        "source": "Le Monde International",
        "cote": "B2",
        "lien": "https://www.lemonde.fr/international/article/2026/06/09/conflit-israel-iran-les-negociateurs-s-activent-malgre-l-escalade-militaire_6700141_3210.html"
      },
      {
        "type": "evenement",
        "zone": "4. Grands Lacs",
        "thematique": "Sécurité & défense",
        "titre": "A Mambasa, l'effondrement du pont Ituri 2 paralyse le trafic sur la RN44",
        "source": "Radio Okapi (RDC)",
        "cote": "F2",
        "lien": "https://www.radiookapi.net/2026/06/09/actualite/societe/mambasa-leffondrement-du-pont-ituri-2-paralyse-le-trafic-sur-la-rn44"
      },
      {
        "type": "evenement",
        "zone": "12. Asie du Sud",
        "thematique": "Humanitaire & social",
        "titre": "Dressing up massacre as military operation does not absolve perpetrator: India on Pakistan at UNSC",
        "source": "The Hindu (Inde)",
        "cote": "F2",
        "lien": "https://www.thehindu.com/news/national/india-at-unsc-pakistans-fitna-al-hindustan-narrative-officially-sponsored-misinformation/article71079143.ece"
      },
      {
        "type": "evenement",
        "zone": "13. Asie du Sud-Est",
        "thematique": "Humanitaire & social",
        "titre": "Séisme aux Philippines : au moins 41 morts ; les opérations de secours ralenties par de nombreuses répliques",
        "source": "Le Monde International",
        "cote": "B2",
        "lien": "https://www.lemonde.fr/international/article/2026/06/09/seisme-aux-philippines-au-moins-41-morts-les-operations-de-secours-ralenties-par-de-nombreuses-repliques_6700129_3210.html"
      },
      {
        "type": "evenement",
        "zone": "9. Europe occidentale",
        "thematique": "Justice & droit international",
        "titre": "Eugène Rwamucyo, condamné à vingt-sept ans de prison pour « complicité de génocide » au Rwanda, revient devant la cour d’assises de Paris",
        "source": "Le Monde International",
        "cote": "B1",
        "lien": "https://www.lemonde.fr/afrique/article/2026/06/09/rwanda-eugene-rwamucyo-condamne-a-vingt-sept-ans-de-prison-pour-complicite-de-genocide-revient-devant-la-cour-d-assises-de-paris_6700090_3212.html"
      },
      {
        "type": "evenement",
        "zone": "4. Grands Lacs",
        "thematique": "Justice & droit international",
        "titre": "Génocide des Tutsis au Rwanda: procès en appel pour Eugène Rwamucyo, condamné à 27 ans de prison",
        "source": "RFI Afrique",
        "cote": "C1",
        "lien": "https://www.rfi.fr/fr/afrique/20260609-g%C3%A9nocide-des-tutsis-au-rwanda-proc%C3%A8s-en-appel-pour-eug%C3%A8ne-rwamucyo-condamn%C3%A9-%C3%A0-27-ans-de-prison"
      },
      {
        "type": "evenement",
        "zone": "13. Asie du Sud-Est",
        "thematique": null,
        "titre": "Un séisme fait au moins 41 morts aux Philippines",
        "source": "Libération International",
        "cote": "C6",
        "lien": "https://www.liberation.fr/international/asie-pacifique/un-seisme-fait-au-moins-15-morts-aux-philippines-20260608_JUEUQOFCGJF5LLDPI74YWS2QX4/"
      }
    ],
    "recompositions": []
  },
  "notesParZone": [
    {
      "zone": "1. Sahel & AO franco.",
      "thematiquesDominantes": [
        "Humanitaire & social",
        "Sécurité & défense",
        "Diplomatie & alliances"
      ],
      "faits": [
        {
          "titre": "Ouagadougou : L’effondrement de la dalle d’un bâtiment R+1 fait des victimes",
          "source": "Minute BF",
          "cote": "F1",
          "lien": "https://www.minute.bf/ouagadougou-leffondrement-de-la-dalle-dun-batiment-r1-fait-des-victimes/",
          "theme": "H"
        },
        {
          "titre": "Drame à Ouagadougou : Un mort et sept blessés dans l’effondrement d’un bâtiment en chantier à Kouba",
          "source": "Net Afrique (BF)",
          "cote": "F1",
          "lien": "https://netafrique.net/drame-a-ouagadougou-un-mort-et-sept-blesses-dans-leffondrement-dun-batiment-en-chantier-a-kouba/",
          "theme": "H"
        },
        {
          "titre": "Burkina Faso: Des manipulateurs de drones kamikaze et des chefs terroristes tués",
          "source": "Net Afrique (BF)",
          "cote": "F2",
          "lien": "https://netafrique.net/burkina-faso-des-manipulateurs-de-drones-kamikaze-et-des-chefs-terroristes-tues/",
          "theme": "S"
        },
        {
          "titre": "Pr Youssoufou Ouédraogo, enseignant d'université à la retraite : « Être fort, c'est être capable de s'arrêter à un feu tricolore à minuit, alors que personne ne vous regarde »",
          "source": "Lefaso.net",
          "cote": "C2",
          "lien": "https://lefaso.net/spip.php?article146998",
          "theme": "D"
        },
        {
          "titre": "Le président béninois attendu au Mali, Sénégal et Guinée-Bissau",
          "source": "Wakat Séra",
          "cote": "A1",
          "lien": "https://www.wakatsera.com/le-president-beninois-attendu-au-mali-senegal-et-guinee-bissau/",
          "theme": "P"
        }
      ],
      "lectureStructuree": "Faits marquants : « Ouagadougou : L’effondrement de la dalle d’un bâtiment R+1 fait des victimes » (Minute BF) ; « Drame à Ouagadougou : Un mort et sept blessés dans l’effondrement d’un bâtiment en chantier à Kouba » (Net Afrique (BF)) ; « Burkina Faso: Des manipulateurs de drones kamikaze et des chefs terroristes tués » (Net Afrique (BF)).\nThématiques actives : Humanitaire & social, Sécurité & défense, Diplomatie & alliances (74 signaux sur la période).\nLecture : la zone pèse sur l'AES via ces dynamiques ; surveiller les signaux de bascule et leurs effets directs/indirects (sécurité, corridors, diplomatie, prix).",
      "confiance": "eleve",
      "proseIA": null
    },
    {
      "zone": "2. AO anglo. & côtière",
      "thematiquesDominantes": [
        "Politique interne & gouvernance",
        "Diplomatie & alliances"
      ],
      "faits": [
        {
          "titre": "Mobilité des étudiants : Vers un protocole d’accord entre le Burkina et le Ghana",
          "source": "Net Afrique (BF)",
          "cote": "F2",
          "lien": "https://netafrique.net/mobilite-des-etudiants-vers-un-protocole-daccord-entre-le-burkina-et-le-ghana/",
          "theme": "D"
        },
        {
          "titre": "Alleged rigging: Stop grandstanding, bring your evidence, Atiku dares ex-SGF Lawal",
          "source": "Vanguard (Nigeria)",
          "cote": "A2",
          "lien": "https://www.vanguardngr.com/2026/06/alleged-rigging-stop-grandstanding-bring-your-evidence-atiku-dares-ex-sgf-lawal/",
          "theme": "P"
        },
        {
          "titre": "Insecurity threatening Nigeria’s education future, says NUT president",
          "source": "Vanguard (Nigeria)",
          "cote": "F2",
          "lien": "https://www.vanguardngr.com/2026/06/insecurity-threatening-nigerias-education-future-says-nut-president/",
          "theme": "P"
        },
        {
          "titre": "PANDEF hails NDC as emerging National Political Force",
          "source": "Vanguard (Nigeria)",
          "cote": "F2",
          "lien": "https://www.vanguardngr.com/2026/06/pandef-hails-ndc-as-emerging-national-political-force/",
          "theme": "D"
        },
        {
          "titre": "2027: Nigeria must move beyond North-South politics, says Baba-Ahmed",
          "source": "Vanguard (Nigeria)",
          "cote": "F1",
          "lien": "https://www.vanguardngr.com/2026/06/2027-nigeria-must-move-beyond-north-south-politics-says-baba-ahmed/",
          "theme": "P"
        }
      ],
      "lectureStructuree": "Faits marquants : « Mobilité des étudiants : Vers un protocole d’accord entre le Burkina et le Ghana » (Net Afrique (BF)) ; « Alleged rigging: Stop grandstanding, bring your evidence, Atiku dares ex-SGF Lawal » (Vanguard (Nigeria)) ; « Insecurity threatening Nigeria’s education future, says NUT president » (Vanguard (Nigeria)).\nThématiques actives : Politique interne & gouvernance, Diplomatie & alliances (61 signaux sur la période).\nLecture : la zone pèse sur l'AES via ces dynamiques ; surveiller les signaux de bascule et leurs effets directs/indirects (sécurité, corridors, diplomatie, prix).",
      "confiance": "eleve",
      "proseIA": null
    },
    {
      "zone": "7. Maghreb & Afr. Nord",
      "thematiquesDominantes": [
        "Sécurité & défense",
        "Politique interne & gouvernance",
        "Diplomatie & alliances"
      ],
      "faits": [
        {
          "titre": "Tourisme | Valorisation du patrimoine urbain en Tunisie",
          "source": "Kapitalis (Tunisie)",
          "cote": "F2",
          "lien": "https://kapitalis.com/tunisie/2026/06/09/tourisme-valorisation-du-patrimoine-urbain-en-tunisie/",
          "theme": "D"
        },
        {
          "titre": "Le Maroc renforce ses capacités de défense avec l’acquisition de drones avancés de fabrication turque",
          "source": "Hespress (Maroc, FR)",
          "cote": "F2",
          "lien": "https://fr.hespress.com/476664-le-maroc-renforce-ses-capacites-de-defense-avec-lacquisition-de-drones-avances-de-fabrication-turque.html",
          "theme": "S"
        },
        {
          "titre": "Warda El-Djazaïria : le récit inédit et bouleversant de son fils Reyad Kesri",
          "source": "TSA — Tout sur l'Algérie",
          "cote": "F2",
          "lien": "https://www.tsa-algerie.com/warda-el-djazairia-le-recit-inedit-et-bouleversant-de-son-fils-reyad-kesri/",
          "theme": "S"
        },
        {
          "titre": "FIFA : Grâce au Maroc, l’Afrique renforce son poids dans l’histoire du Mondial",
          "source": "Hespress (Maroc, FR)",
          "cote": "F2",
          "lien": "https://fr.hespress.com/476679-fifa-grace-au-maroc-lafrique-renforce-son-poids-dans-lhistoire-du-mondial.html",
          "theme": "P"
        },
        {
          "titre": "Mondial 2026 : Le Brésilien Guimarães voit dans le Maroc l’une des meilleures équipes de sa génération",
          "source": "Hespress (Maroc, FR)",
          "cote": "F2",
          "lien": "https://fr.hespress.com/476683-mondial-2026-le-bresilien-guimaraes-voit-dans-le-maroc-lune-des-meilleures-equipes-de-sa-generation.html",
          "theme": "P"
        }
      ],
      "lectureStructuree": "Faits marquants : « Tourisme | Valorisation du patrimoine urbain en Tunisie » (Kapitalis (Tunisie)) ; « Le Maroc renforce ses capacités de défense avec l’acquisition de drones avancés de fabrication turque » (Hespress (Maroc, FR)) ; « Warda El-Djazaïria : le récit inédit et bouleversant de son fils Reyad Kesri » (TSA — Tout sur l'Algérie).\nThématiques actives : Sécurité & défense, Politique interne & gouvernance, Diplomatie & alliances (24 signaux sur la période).\nLecture : la zone pèse sur l'AES via ces dynamiques ; surveiller les signaux de bascule et leurs effets directs/indirects (sécurité, corridors, diplomatie, prix).",
      "confiance": "eleve",
      "proseIA": null
    }
  ],
  "notesProspectives": [
    {
      "zone": "1. Sahel & AO franco.",
      "hypothese": "Si la dynamique « 1. Sahel & AO franco. » (stable) se poursuit a 3-6 mois, l'impact sur l'AES s'accentue.",
      "signauxASurveiller": [
        "Frequence et localisation des incidents",
        "Reactions diplomatiques (CEDEAO/UA/ONU)",
        "Etat des corridors logistiques",
        "Prix (or, carburant, cereales)"
      ],
      "confiance": "faible",
      "proseIA": null
    },
    {
      "zone": "2. AO anglo. & côtière",
      "hypothese": "Si la dynamique « 2. AO anglo. & côtière » (stable) se poursuit a 3-6 mois, l'impact sur l'AES s'accentue.",
      "signauxASurveiller": [
        "Frequence et localisation des incidents",
        "Reactions diplomatiques (CEDEAO/UA/ONU)",
        "Etat des corridors logistiques",
        "Prix (or, carburant, cereales)"
      ],
      "confiance": "faible",
      "proseIA": null
    },
    {
      "zone": "7. Maghreb & Afr. Nord",
      "hypothese": "Si la dynamique « 7. Maghreb & Afr. Nord » (stable) se poursuit a 3-6 mois, l'impact sur l'AES s'accentue.",
      "signauxASurveiller": [
        "Frequence et localisation des incidents",
        "Reactions diplomatiques (CEDEAO/UA/ONU)",
        "Etat des corridors logistiques",
        "Prix (or, carburant, cereales)"
      ],
      "confiance": "faible",
      "proseIA": null
    }
  ],
  "etudesThematiques": [
    {
      "code": "P",
      "libelle": "Politique interne & gouvernance",
      "volume": 100,
      "direction": "stable",
      "faitsSaillants": [
        {
          "titre": "If Bardella wins: Scenarios for a far-right presidency in France",
          "source": "ECFR — European Council on Foreign Relations",
          "cote": "A2",
          "lien": "https://ecfr.eu/publication/if-bardella-wins-scenarios-for-a-far-right-presidency-in-france/"
        },
        {
          "titre": "Le président béninois attendu au Mali, Sénégal et Guinée-Bissau",
          "source": "Wakat Séra",
          "cote": "A1",
          "lien": "https://www.wakatsera.com/le-president-beninois-attendu-au-mali-senegal-et-guinee-bissau/"
        },
        {
          "titre": "Deuil dans le football burkinabè : Décès de l’ex-défenseur des Étalons Ben Aziz Zagré des suites d’un cancer à 27 ans",
          "source": "Net Afrique (BF)",
          "cote": "F2",
          "lien": "https://netafrique.net/deuil-dans-le-football-burkinabe-deces-de-lex-defenseur-des-etalons-ben-aziz-zagre-des-suites-dun-cancer-a-27-ans/"
        },
        {
          "titre": "Un prêtre congolais vivant en Italie appelle les Burkinabè à soutenir le Président Traoré",
          "source": "Net Afrique (BF)",
          "cote": "F2",
          "lien": "https://netafrique.net/un-pretre-congolais-vivant-en-italie-appelle-les-burkinabe-a-soutenir-le-president-traore/"
        },
        {
          "titre": "Burkina : Le gouvernement suspend l’organisation des concours de beauté",
          "source": "Net Afrique (BF)",
          "cote": "F1",
          "lien": "https://netafrique.net/burkina-le-gouvernement-suspend-lorganisation-des-concours-de-beaute/"
        }
      ],
      "lecture": "Politique interne & gouvernance : 100 signaux sur la période (tendance stable). Faits marquants : « If Bardella wins: Scenarios for a far-right presidency in France » (ECFR — European Council on Foreign Relations) ; « Le président béninois attendu au Mali, Sénégal et Guinée-Bissau » (Wakat Séra) ; « Deuil dans le football burkinabè : Décès de l’ex-défenseur des Étalons Ben Aziz Zagré des suites d’un cancer à 27 ans » (Net Afrique (BF)).",
      "blocs": [
        "afrique (32)",
        "occident_fr (15)",
        "occident_us (13)",
        "golfe_mo (12)"
      ],
      "sources": [
        "Vanguard (Nigeria)",
        "MyJoyOnline (Ghana)",
        "Dawn (Pakistan)",
        "Le Monde International",
        "Le Soleil (Sénégal)"
      ],
      "proseIA": null
    },
    {
      "code": "E",
      "libelle": "Économie & ressources",
      "volume": 82,
      "direction": "stable",
      "faitsSaillants": [
        {
          "titre": "Burkina/Médias : Des travailleurs de Burkina Info dénoncent plusieurs mois d’arriérés de salaire",
          "source": "Minute BF",
          "cote": "F2",
          "lien": "https://www.minute.bf/burkina-medias-des-travailleurs-de-burkina-info-denoncent-plusieurs-mois-darrieres-de-salaire/"
        },
        {
          "titre": "CAGEI | Appel à candidatures : Formation certifiante en Administration et gestion des organisations",
          "source": "Burkina24",
          "cote": "C2",
          "lien": "https://burkina24.com/2026/06/09/cagei-appel-a-candidatures-formation-certifiante-en-administration-et-gestion-des-organisations/"
        },
        {
          "titre": "Burkina : Les pompiers invitent les parents à renforcer leur vigilance pour éviter les drames liés aux vacances scolaires",
          "source": "Net Afrique (BF)",
          "cote": "F2",
          "lien": "https://netafrique.net/burkina-les-pompiers-invitent-les-parents-a-renforcer-leur-vigilance-pour-eviter-les-drames-lies-aux-vacances-scolaires/"
        },
        {
          "titre": "REGLEMENTATION DU SECTEUR DES CYCLES, CYCLOMOTEURS ET MOTOCYCLES AU BURKINA : Comment faire des omelettes sans casser les œufs ?",
          "source": "Le Pays (BF)",
          "cote": "F2",
          "lien": "https://lepays.bf/reglementation-du-secteur-des-cycles-cyclomoteurs-et-motocycles-au-burkina-comment-faire-des-omelettes-sans-casser-les-oeufs/"
        },
        {
          "titre": "La nouvelle économie politique",
          "source": "Sidwaya",
          "cote": "C2",
          "lien": "https://www.sidwaya.info/commentairesid-du-9-6-2026-mac-zango-commentaire-la-nouvelle-economie-politique-comme-le-rappelait-fort-a-propos-notre-editorialiste-hier-lundi/"
        }
      ],
      "lecture": "Économie & ressources : 82 signaux sur la période (tendance stable). Faits marquants : « Burkina/Médias : Des travailleurs de Burkina Info dénoncent plusieurs mois d’arriérés de salaire » (Minute BF) ; « CAGEI | Appel à candidatures : Formation certifiante en Administration et gestion des organisations » (Burkina24) ; « Burkina : Les pompiers invitent les parents à renforcer leur vigilance pour éviter les drames liés aux vacances scolaires » (Net Afrique (BF)).",
      "blocs": [
        "afrique (32)",
        "autre (11)",
        "bf_local (7)",
        "russie (7)"
      ],
      "sources": [
        "MyJoyOnline (Ghana)",
        "Dawn (Pakistan)",
        "South China Morning Post",
        "Mediaguinee",
        "Médias 24 (Maroc)"
      ],
      "proseIA": null
    },
    {
      "code": "S",
      "libelle": "Sécurité & défense",
      "volume": 59,
      "direction": "stable",
      "faitsSaillants": [
        {
          "titre": "Burkina Faso: Des manipulateurs de drones kamikaze et des chefs terroristes tués",
          "source": "Net Afrique (BF)",
          "cote": "F2",
          "lien": "https://netafrique.net/burkina-faso-des-manipulateurs-de-drones-kamikaze-et-des-chefs-terroristes-tues/"
        },
        {
          "titre": "Solidarité envers les veuves et orphelins des FDS: le RCPB fait don de vivres d’une valeur de 5 millions F CFA",
          "source": "Sidwaya",
          "cote": "C2",
          "lien": "https://www.sidwaya.info/solidarite-envers-les-veuves-et-orphelins-des-fds-le-rcpb-fait-don-de-vivres-dune-valeur-de-5-millions-f-cfa/"
        },
        {
          "titre": "Cour royale de Tiébélé: des femmes kassena gravent des valeurs culturelles",
          "source": "Sidwaya",
          "cote": "C2",
          "lien": "https://www.sidwaya.info/cour-royale-de-tiebele-des-femmes-kassena-gravent-des-valeurs-culturelles/"
        },
        {
          "titre": "Lutte antiterroriste : Plusieurs dizaines Guideurs Aériens Tactiques Avancés prêts à servir la nation",
          "source": "Minute BF",
          "cote": "F2",
          "lien": "https://www.minute.bf/lutte-antiterroriste-plusieurs-dizaines-guideurs-aeriens-tactiques-avances-prets-a-servir-la-nation/"
        },
        {
          "titre": "Cyclisme : Le Tour du Faso réintègre le circuit international UCI",
          "source": "Net Afrique (BF)",
          "cote": "F2",
          "lien": "https://netafrique.net/cyclisme-le-tour-du-faso-reintegre-le-circuit-international-uci/"
        }
      ],
      "lecture": "Sécurité & défense : 59 signaux sur la période (tendance stable). Faits marquants : « Burkina Faso: Des manipulateurs de drones kamikaze et des chefs terroristes tués » (Net Afrique (BF)) ; « Solidarité envers les veuves et orphelins des FDS: le RCPB fait don de vivres d’une valeur de 5 millions F CFA » (Sidwaya) ; « Cour royale de Tiébélé: des femmes kassena gravent des valeurs culturelles » (Sidwaya).",
      "blocs": [
        "occident_fr (18)",
        "russie (11)",
        "afrique (9)",
        "bf_local (6)"
      ],
      "sources": [
        "TASS (Russie, EN)",
        "Le Monde International",
        "Dawn (Pakistan)",
        "Sidwaya",
        "RFI Afrique"
      ],
      "proseIA": null
    },
    {
      "code": "D",
      "libelle": "Diplomatie & alliances",
      "volume": 55,
      "direction": "stable",
      "faitsSaillants": [
        {
          "titre": "Pr Youssoufou Ouédraogo, enseignant d'université à la retraite : « Être fort, c'est être capable de s'arrêter à un feu tricolore à minuit, alors que personne ne vous regarde »",
          "source": "Lefaso.net",
          "cote": "C2",
          "lien": "https://lefaso.net/spip.php?article146998"
        },
        {
          "titre": "Mobilité des étudiants : Vers un protocole d’accord entre le Burkina et le Ghana",
          "source": "Net Afrique (BF)",
          "cote": "F2",
          "lien": "https://netafrique.net/mobilite-des-etudiants-vers-un-protocole-daccord-entre-le-burkina-et-le-ghana/"
        },
        {
          "titre": "Diplomatie: les priorités au cœur du voyage de Wadagni au Sénégal, au Mali et en Guinée-Bissau",
          "source": "Bénin Web TV",
          "cote": "A1",
          "lien": "https://beninwebtv.com/diplomatie-les-priorites-au-coeur-du-voyage-de-wadagni-au-senegal-au-mali-et-en-guinee-bissau/"
        },
        {
          "titre": "PANDEF hails NDC as emerging National Political Force",
          "source": "Vanguard (Nigeria)",
          "cote": "F2",
          "lien": "https://www.vanguardngr.com/2026/06/pandef-hails-ndc-as-emerging-national-political-force/"
        },
        {
          "titre": "Donald Trump enrage contre le Sultanat d’Oman !",
          "source": "Kapitalis (Tunisie)",
          "cote": "F2",
          "lien": "https://kapitalis.com/tunisie/2026/06/09/donald-trump-enrage-contre-le-sultanat-doman/"
        }
      ],
      "lecture": "Diplomatie & alliances : 55 signaux sur la période (tendance stable). Faits marquants : « Pr Youssoufou Ouédraogo, enseignant d'université à la retraite : « Être fort, c'est être capable de s'arrêter à un feu tricolore à minuit, alors que personne ne vous regarde » » (Lefaso.net) ; « Mobilité des étudiants : Vers un protocole d’accord entre le Burkina et le Ghana » (Net Afrique (BF)) ; « Diplomatie: les priorités au cœur du voyage de Wadagni au Sénégal, au Mali et en Guinée-Bissau » (Bénin Web TV).",
      "blocs": [
        "afrique (23)",
        "autre (7)",
        "golfe_mo (7)",
        "turquie (6)"
      ],
      "sources": [
        "Anadolu Agency (Turquie)",
        "The Hindu (Inde)",
        "Vanguard (Nigeria)",
        "Punch (Nigeria)",
        "Dawn (Pakistan)"
      ],
      "proseIA": null
    }
  ],
  "byConflict": {
    "c_aes": {
      "id": "c_aes",
      "name": "Sahel/AES",
      "volume": 91,
      "themesDominants": [
        "Politique interne & gouvernance",
        "Humanitaire & social",
        "Sécurité & défense"
      ],
      "faits": [
        {
          "titre": "If Bardella wins: Scenarios for a far-right presidency in France",
          "source": "ECFR — European Council on Foreign Relations",
          "cote": "A2",
          "lien": "https://ecfr.eu/publication/if-bardella-wins-scenarios-for-a-far-right-presidency-in-france/",
          "theme": "P"
        },
        {
          "titre": "Ouagadougou : L’effondrement de la dalle d’un bâtiment R+1 fait des victimes",
          "source": "Minute BF",
          "cote": "F1",
          "lien": "https://www.minute.bf/ouagadougou-leffondrement-de-la-dalle-dun-batiment-r1-fait-des-victimes/",
          "theme": "H"
        },
        {
          "titre": "Drame à Ouagadougou : Un mort et sept blessés dans l’effondrement d’un bâtiment en chantier à Kouba",
          "source": "Net Afrique (BF)",
          "cote": "F1",
          "lien": "https://netafrique.net/drame-a-ouagadougou-un-mort-et-sept-blesses-dans-leffondrement-dun-batiment-en-chantier-a-kouba/",
          "theme": "H"
        },
        {
          "titre": "Burkina Faso: Des manipulateurs de drones kamikaze et des chefs terroristes tués",
          "source": "Net Afrique (BF)",
          "cote": "F2",
          "lien": "https://netafrique.net/burkina-faso-des-manipulateurs-de-drones-kamikaze-et-des-chefs-terroristes-tues/",
          "theme": "S"
        },
        {
          "titre": "Pr Youssoufou Ouédraogo, enseignant d'université à la retraite : « Être fort, c'est être capable de s'arrêter à un feu tricolore à minuit, alors que personne ne vous regarde »",
          "source": "Lefaso.net",
          "cote": "C2",
          "lien": "https://lefaso.net/spip.php?article146998",
          "theme": "D"
        },
        {
          "titre": "Le président béninois attendu au Mali, Sénégal et Guinée-Bissau",
          "source": "Wakat Séra",
          "cote": "A1",
          "lien": "https://www.wakatsera.com/le-president-beninois-attendu-au-mali-senegal-et-guinee-bissau/",
          "theme": "P"
        }
      ],
      "enjeu": "Inventer un modèle politique africain qui combine souveraineté affichée et efficacité sécuritaire — sans y être encore parvenu.",
      "consequencesAES": "Maximale (priorité 1) : Le Burkina Faso EST le théâtre central de ce conflit. Toute analyse sahélienne est de facto une analyse burkinabè. : Le BF est l'État le plus exposé du trio AES en termes de pression jihadiste : ~40 % du territoire hors contrôle effectif, attaques mensuelles record en glissem…",
      "lectureStructuree": "SITUATION (live) — 91 dépêches sur la période, dominante : Politique interne & gouvernance, Humanitaire & social, Sécurité & défense.\nFaits saillants : « If Bardella wins: Scenarios for a far-right presidency in France » (ECFR — European Council on Foreign Relations, cote A2) ; « Ouagadougou : L’effondrement de la dalle d’un bâtiment R+1 fait des victimes » (Minute BF, cote F1) ; « Drame à Ouagadougou : Un mort et sept blessés dans l’effondrement d’un bâtiment en chantier à Kouba » (Net Afrique (BF), cote F1).\n\nENJEU CENTRAL — Inventer un modèle politique africain qui combine souveraineté affichée et efficacité sécuritaire — sans y être encore parvenu.\n\nPOURQUOI — C'est la rupture géopolitique africaine la plus profonde depuis les indépendances. Elle redistribue les cartes de l'influence en Afrique de l'Ouest, fragilise la CEDEAO, ouvre la voie à de nouveaux partenaires (Russie, Chine, Iran, Turquie, Émirats), et pose la question de la viabilité du modèle militaro-plébiscitaire face à une menace jihadiste qui continue de progresser.\n\nIMPACT POUR L'AES — Maximale (priorité 1) : Le Burkina Faso EST le théâtre central de ce conflit. Toute analyse sahélienne est de facto une analyse burkinabè. : Le BF est l'État le plus exposé du trio AES en termes de pression jihadiste : ~40 % du territoire hors contrôle effectif, attaques mensuelles record en glissem…\n\nSCÉNARIOS —\n• Tendanciel — érosion lente (55%) : Les juntes tiennent par la force et la popularité urbaine, mais perdent du territoire rural. Wagner reste mais ne stabilise pas. JNIM consolide ses émirats. Attaques sur capitales sans les prendre. Sortie partielle F CFA, instabilité monétaire gérée.\n• Rupture — chute d'un État (25%) : Un État (probablement BF ou Mali) bascule : prise de capitale ou effondrement militaire complet. Gouvernement transitionnel forcé d'inclure jihadistes. Onde de choc régionale, exode massif, intervention extérieure non-occidentale possible (Égypte, Algérie).\n\nÀ SURVEILLER — Une attaque réussie sur Ouagadougou-centre ou Bamako (rupture systémique). ; L'extension côtière de la guerre (Bénin, Togo, Côte d'Ivoire). ; La sortie effective du F CFA et la naissance d'une monnaie AES.",
      "prospective": "12-24 mois : statu quo dégradé probable, perte de territoires ruraux, popularité urbaine maintenue.",
      "confiance": "eleve",
      "proseIA": null
    },
    "c_iran_il": {
      "id": "c_iran_il",
      "name": "Iran-Israël",
      "volume": 148,
      "themesDominants": [
        "Politique interne & gouvernance",
        "Sécurité & défense",
        "Diplomatie & alliances"
      ],
      "faits": [
        {
          "titre": "If Bardella wins: Scenarios for a far-right presidency in France",
          "source": "ECFR — European Council on Foreign Relations",
          "cote": "A2",
          "lien": "https://ecfr.eu/publication/if-bardella-wins-scenarios-for-a-far-right-presidency-in-france/",
          "theme": "P"
        },
        {
          "titre": "Cyclisme : Le Tour du Faso réintègre le circuit international UCI",
          "source": "Net Afrique (BF)",
          "cote": "F2",
          "lien": "https://netafrique.net/cyclisme-le-tour-du-faso-reintegre-le-circuit-international-uci/",
          "theme": "S"
        },
        {
          "titre": "Guerre au Moyen-Orient : les négociateurs s’activent malgré l’escalade militaire",
          "source": "Le Monde International",
          "cote": "B2",
          "lien": "https://www.lemonde.fr/international/article/2026/06/09/conflit-israel-iran-les-negociateurs-s-activent-malgre-l-escalade-militaire_6700141_3210.html",
          "theme": "S"
        },
        {
          "titre": "Alleged rigging: Stop grandstanding, bring your evidence, Atiku dares ex-SGF Lawal",
          "source": "Vanguard (Nigeria)",
          "cote": "A2",
          "lien": "https://www.vanguardngr.com/2026/06/alleged-rigging-stop-grandstanding-bring-your-evidence-atiku-dares-ex-sgf-lawal/",
          "theme": "P"
        },
        {
          "titre": "2027: Nigeria must move beyond North-South politics, says Baba-Ahmed",
          "source": "Vanguard (Nigeria)",
          "cote": "F1",
          "lien": "https://www.vanguardngr.com/2026/06/2027-nigeria-must-move-beyond-north-south-politics-says-baba-ahmed/",
          "theme": "P"
        },
        {
          "titre": "Donald Trump enrage contre le Sultanat d’Oman !",
          "source": "Kapitalis (Tunisie)",
          "cote": "F2",
          "lien": "https://kapitalis.com/tunisie/2026/06/09/donald-trump-enrage-contre-le-sultanat-doman/",
          "theme": "D"
        }
      ],
      "enjeu": "La question nucléaire iranienne et la survie du régime des Pasdaran détermineront la stabilité régionale pour 20 ans.",
      "consequencesAES": "Élevée (impact indirect majeur) : Le BF n'est pas acteur direct mais subit la totalité des chocs économiques et géopolitiques de l'embrasement moyen-oriental. : Réseaux jihadistes sahéliens (JNIM, EIGS) bénéficient indirectement de l'effervescence post-Gaza : recrutement, financement Golfe, diffusio…",
      "lectureStructuree": "SITUATION (live) — 148 dépêches sur la période, dominante : Politique interne & gouvernance, Sécurité & défense, Diplomatie & alliances.\nFaits saillants : « If Bardella wins: Scenarios for a far-right presidency in France » (ECFR — European Council on Foreign Relations, cote A2) ; « Cyclisme : Le Tour du Faso réintègre le circuit international UCI » (Net Afrique (BF), cote F2) ; « Guerre au Moyen-Orient : les négociateurs s’activent malgré l’escalade militaire » (Le Monde International, cote B2).\n\nENJEU CENTRAL — La question nucléaire iranienne et la survie du régime des Pasdaran détermineront la stabilité régionale pour 20 ans.\n\nPOURQUOI — Le Moyen-Orient connaît sa plus profonde recomposition depuis 1979. L'affaiblissement de l'arc chiite ouvre une fenêtre incertaine : soit un nouvel ordre stable autour des puissances du Golfe, soit une escalade directe Iran-Israël-USA. Les chocs pétroliers potentiels via le détroit d'Ormuz frappent directement les économies importatrices comme le Burkina Faso. ⚠️ Certains éléments de cette analyse sont prospectifs — vérifiez avec les dernières sources IRIS/ICG.\n\nIMPACT POUR L'AES — Élevée (impact indirect majeur) : Le BF n'est pas acteur direct mais subit la totalité des chocs économiques et géopolitiques de l'embrasement moyen-oriental. : Réseaux jihadistes sahéliens (JNIM, EIGS) bénéficient indirectement de l'effervescence post-Gaza : recrutement, financement Golfe, diffusio…\n\nSCÉNARIOS —\n• Tendanciel — Iran affaibli, ordre US-saoudien (40%) : Régime iranien survit mais affaibli. Reconstruction proxies lente. Saoudiens dominent OPEC+ et arbitrent Levant. Israël intègre normalisation arabe (extension Abraham). Sahel et Russie reviennent par défaut.\n• Rupture — junte Pasdaran nucléaire (25%) : CGRI prend le pouvoir, sortie TNP, accélération bombe. Sanctions totales mais marché chinois maintenu. Course aux armements régionale (Saoudite, Turquie). Risque frappes israéliennes répétées.\n\nÀ SURVEILLER — L'état réel du programme nucléaire iranien (enrichissement résiduel ?). ; Le détroit d'Ormuz : toute fermeture déclencherait un choc pétrolier mondial. ; Le sort des sites nucléaires Fordo/Natanz : capacité résiduelle d'enrichir ?",
      "prospective": "6-12 mois : crise économique aiguë en Iran, possible accélération nucléaire clandestine.",
      "confiance": "eleve",
      "proseIA": null
    },
    "c_ukr": {
      "id": "c_ukr",
      "name": "Ukraine-Russie",
      "volume": 50,
      "themesDominants": [
        "Sécurité & défense",
        "Politique interne & gouvernance"
      ],
      "faits": [
        {
          "titre": "If Bardella wins: Scenarios for a far-right presidency in France",
          "source": "ECFR — European Council on Foreign Relations",
          "cote": "A2",
          "lien": "https://ecfr.eu/publication/if-bardella-wins-scenarios-for-a-far-right-presidency-in-france/",
          "theme": "P"
        },
        {
          "titre": "Deuil dans le football burkinabè : Décès de l’ex-défenseur des Étalons Ben Aziz Zagré des suites d’un cancer à 27 ans",
          "source": "Net Afrique (BF)",
          "cote": "F2",
          "lien": "https://netafrique.net/deuil-dans-le-football-burkinabe-deces-de-lex-defenseur-des-etalons-ben-aziz-zagre-des-suites-dun-cancer-a-27-ans/",
          "theme": "P"
        },
        {
          "titre": "Cyclisme : Le Tour du Faso réintègre le circuit international UCI",
          "source": "Net Afrique (BF)",
          "cote": "F2",
          "lien": "https://netafrique.net/cyclisme-le-tour-du-faso-reintegre-le-circuit-international-uci/",
          "theme": "S"
        },
        {
          "titre": "À partir de demain, la guerre en Ukraine sera aussi longue que la Première Guerre mondiale",
          "source": "Le Grand Continent",
          "cote": "A1",
          "lien": "https://legrandcontinent.eu/fr/2026/06/09/a-partir-de-demain-la-guerre-en-ukraine-sera-aussi-longue-que-la-premiere-guerre-mondiale/",
          "theme": "S"
        },
        {
          "titre": "Ukraine’s Neighbors Seek Shelter as More and More Drones Fly Overhead",
          "source": "NYT World",
          "cote": "B2",
          "lien": "https://www.nytimes.com/2026/06/09/world/europe/russia-ukraine-drones-nato-lithuania-romania.html",
          "theme": "S"
        },
        {
          "titre": "EN DIRECT, guerre en Ukraine : dans la région de Kharkiv, les frappes russes nocturnes ont fait quatre morts, selon un nouveau bilan des autorités locales",
          "source": "Le Monde International",
          "cote": "B2",
          "lien": "https://www.lemonde.fr/international/live/2026/06/09/en-direct-guerre-en-ukraine-dans-la-region-de-kharkiv-les-frappes-russes-nocturnes-ont-fait-quatre-morts-selon-un-nouveau-bilan-des-autorites-locales_6698620_3210.html",
          "theme": "S"
        }
      ],
      "enjeu": "L'Ukraine est trop grande pour être conquise et trop importante pour être abandonnée. Le conflit tend vers un blocage prolongé que personne ne sait résoudre.",
      "consequencesAES": "Élevée (Russie = partenaire stratégique BF) : La guerre russe en Ukraine engage directement le partenaire militaire principal du BF (Africa Corps) et structure ses capacités. : Africa Corps (héritier Wagner) : ~1 200-2 000 instructeurs/combattants au Mali, présence BF moins documentée mais croissant…",
      "lectureStructuree": "SITUATION (live) — 50 dépêches sur la période, dominante : Sécurité & défense, Politique interne & gouvernance.\nFaits saillants : « If Bardella wins: Scenarios for a far-right presidency in France » (ECFR — European Council on Foreign Relations, cote A2) ; « Deuil dans le football burkinabè : Décès de l’ex-défenseur des Étalons Ben Aziz Zagré des suites d’un cancer à 27 ans » (Net Afrique (BF), cote F2) ; « Cyclisme : Le Tour du Faso réintègre le circuit international UCI » (Net Afrique (BF), cote F2).\n\nENJEU CENTRAL — L'Ukraine est trop grande pour être conquise et trop importante pour être abandonnée. Le conflit tend vers un blocage prolongé que personne ne sait résoudre.\n\nPOURQUOI — C'est la première guerre européenne de haute intensité depuis 1945 et le test décisif de l'ordre international post-Guerre froide. Si la Russie obtient des concessions par la force, la frontière taïwanaise, sahélienne et caucasienne deviennent négociables par les armes. C'est aussi un test pour le réarmement européen et la crédibilité de l'OTAN sans soutien américain.\n\nIMPACT POUR L'AES — Élevée (Russie = partenaire stratégique BF) : La guerre russe en Ukraine engage directement le partenaire militaire principal du BF (Africa Corps) et structure ses capacités. : Africa Corps (héritier Wagner) : ~1 200-2 000 instructeurs/combattants au Mali, présence BF moins documentée mais croissant…\n\nSCÉNARIOS —\n• Tendanciel — gel armé (40%) : Trump impose cessez-le-feu sur ligne actuelle. Pas de reconnaissance Crimée/Donbass. Pas de garanties OTAN. Conflit gelé type Coréen. Reconstruction lente, militarisation pérenne.\n• Rupture — effondrement russe (20%) : Crise économique aiguë + défaite militaire ponctuelle + crise succession ouvrent transition. Risque mais aussi opportunité historique.\n\nÀ SURVEILLER — Les décrets de Trump sur l'aide militaire (effectif effectif sur 6 mois). ; L'évolution du front : reprise russe ou ukrainienne dans Sumy/Kharkiv/Donetsk. ; Les capacités économiques russes après 4 ans d'économie de guerre (taux d'intérêt 21%, démographie négative).",
      "prospective": "12-24 mois : forte probabilité de gel imposé par Trump sur la ligne actuelle, sans paix.",
      "confiance": "eleve",
      "proseIA": null
    },
    "c_gaza": {
      "id": "c_gaza",
      "name": "Gaza-Liban",
      "volume": 99,
      "themesDominants": [
        "Sécurité & défense",
        "Politique interne & gouvernance",
        "Diplomatie & alliances"
      ],
      "faits": [
        {
          "titre": "If Bardella wins: Scenarios for a far-right presidency in France",
          "source": "ECFR — European Council on Foreign Relations",
          "cote": "A2",
          "lien": "https://ecfr.eu/publication/if-bardella-wins-scenarios-for-a-far-right-presidency-in-france/",
          "theme": "P"
        },
        {
          "titre": "Guerre au Moyen-Orient : les négociateurs s’activent malgré l’escalade militaire",
          "source": "Le Monde International",
          "cote": "B2",
          "lien": "https://www.lemonde.fr/international/article/2026/06/09/conflit-israel-iran-les-negociateurs-s-activent-malgre-l-escalade-militaire_6700141_3210.html",
          "theme": "S"
        },
        {
          "titre": "Gaza: les ordres d'évacuation créent un vent de panique chez les Gazaouis",
          "source": "RFI Moyen-Orient",
          "cote": "C2",
          "lien": "https://www.rfi.fr/fr/moyen-orient/20260609-gaza-les-ordres-d-%C3%A9vacuation-cr%C3%A9ent-un-vent-de-panique-chez-les-gazaouis",
          "theme": "S"
        },
        {
          "titre": "India's key objectives in Afghanistan solely driven by singular goal of destabilising Pakistan, envoy tells UNSC",
          "source": "Dawn (Pakistan)",
          "cote": "F2",
          "lien": "https://www.dawn.com/news/2006316/indias-key-objectives-in-afghanistan-solely-driven-by-singular-goal-of-destabilising-pakistan-envoy-tells-unsc",
          "theme": "S"
        },
        {
          "titre": "Donald Trump enrage contre le Sultanat d’Oman !",
          "source": "Kapitalis (Tunisie)",
          "cote": "F2",
          "lien": "https://kapitalis.com/tunisie/2026/06/09/donald-trump-enrage-contre-le-sultanat-doman/",
          "theme": "D"
        },
        {
          "titre": "Les Palestiniens, à Gaza comme en Cisjordanie occupée, pris en étau entre les colons israéliens et le Hamas, alerte une commission mandatée par l’ONU",
          "source": "Le Monde International",
          "cote": "A2",
          "lien": "https://www.lemonde.fr/international/article/2026/06/09/les-palestiniens-pris-en-etau-entre-les-colons-israeliens-et-le-hamas-alerte-une-commission-mandatee-par-l-onu_6700133_3210.html",
          "theme": "S"
        }
      ],
      "enjeu": "Sans horizon politique palestinien crédible (deux États ou alternative), aucun cessez-le-feu ne sera durable. Le « jour d'après » est la vraie question, pas le « jour pendant ».",
      "consequencesAES": "Modérée (impact diplomatique et symbolique) : Le BF n'est pas acteur direct mais la cause palestinienne structure la rhétorique anti-occidentale du régime et l'imaginaire panafricain. : Pas d'impact sécuritaire direct. Mais radicalisation idéologique via réseaux numériques mobilise jihadistes sahéli…",
      "lectureStructuree": "SITUATION (live) — 99 dépêches sur la période, dominante : Sécurité & défense, Politique interne & gouvernance, Diplomatie & alliances.\nFaits saillants : « If Bardella wins: Scenarios for a far-right presidency in France » (ECFR — European Council on Foreign Relations, cote A2) ; « Guerre au Moyen-Orient : les négociateurs s’activent malgré l’escalade militaire » (Le Monde International, cote B2) ; « Gaza: les ordres d'évacuation créent un vent de panique chez les Gazaouis » (RFI Moyen-Orient, cote C2).\n\nENJEU CENTRAL — Sans horizon politique palestinien crédible (deux États ou alternative), aucun cessez-le-feu ne sera durable. Le « jour d'après » est la vraie question, pas le « jour pendant ».\n\nPOURQUOI — Au-delà du drame humanitaire (~50 000 morts à Gaza, famine documentée), cette guerre teste la crédibilité du droit international (procès CIJ, plaintes CPI), polarise les opinions occidentales et du Sud global, et reconfigure le Moyen-Orient. Elle bloque la normalisation arabe d'Israël et alimente partout les récits anti-impérialistes — y compris au Burkina Faso.\n\nIMPACT POUR L'AES — Modérée (impact diplomatique et symbolique) : Le BF n'est pas acteur direct mais la cause palestinienne structure la rhétorique anti-occidentale du régime et l'imaginaire panafricain. : Pas d'impact sécuritaire direct. Mais radicalisation idéologique via réseaux numériques mobilise jihadistes sahéli…\n\nSCÉNARIOS —\n• Tendanciel — guerre prolongée à intensité variable (45%) : Pas de cessez-le-feu durable. Opérations IDF récurrentes Gaza et Cisjordanie. Tirs sporadiques Sud-Liban. Hamas se reconstitue lentement. Reconstruction quasi-nulle. Crise humanitaire chronique.\n• Recomposition — plan régional Trump/Saoudien (25%) : Force internationale arabe (saoudienne, EAU, Égypte) à Gaza. Réforme Autorité palestinienne. Reconstruction financée Golfe. Normalisation saoudienne phase 1. Cisjordanie en attente.\n\nÀ SURVEILLER — Le plan régional Trump-Saoudien (force internationale arabe à Gaza ?). ; L'évolution Cisjordanie : risque de 3e Intifada. ; La survie de la coalition Netanyahou (otages, procès, élections).",
      "prospective": "12-24 mois : probable statu quo dégradé, occupation militaire permanente Gaza, raids Cisjordanie.",
      "confiance": "eleve",
      "proseIA": null
    },
    "c_sdn": {
      "id": "c_sdn",
      "name": "Soudan",
      "volume": 28,
      "themesDominants": [
        "Sécurité & défense",
        "Politique interne & gouvernance"
      ],
      "faits": [
        {
          "titre": "If Bardella wins: Scenarios for a far-right presidency in France",
          "source": "ECFR — European Council on Foreign Relations",
          "cote": "A2",
          "lien": "https://ecfr.eu/publication/if-bardella-wins-scenarios-for-a-far-right-presidency-in-france/",
          "theme": "P"
        },
        {
          "titre": "À partir de demain, la guerre en Ukraine sera aussi longue que la Première Guerre mondiale",
          "source": "Le Grand Continent",
          "cote": "A1",
          "lien": "https://legrandcontinent.eu/fr/2026/06/09/a-partir-de-demain-la-guerre-en-ukraine-sera-aussi-longue-que-la-premiere-guerre-mondiale/",
          "theme": "S"
        },
        {
          "titre": "Insecurity threatening Nigeria’s education future, says NUT president",
          "source": "Vanguard (Nigeria)",
          "cote": "F2",
          "lien": "https://www.vanguardngr.com/2026/06/insecurity-threatening-nigerias-education-future-says-nut-president/",
          "theme": "P"
        },
        {
          "titre": "India's key objectives in Afghanistan solely driven by singular goal of destabilising Pakistan, envoy tells UNSC",
          "source": "Dawn (Pakistan)",
          "cote": "F2",
          "lien": "https://www.dawn.com/news/2006316/indias-key-objectives-in-afghanistan-solely-driven-by-singular-goal-of-destabilising-pakistan-envoy-tells-unsc",
          "theme": "S"
        },
        {
          "titre": "AJK braces for long march as tensions persist",
          "source": "Dawn (Pakistan)",
          "cote": "F2",
          "lien": "https://www.dawn.com/news/2006256/ajk-braces-for-long-march-as-tensions-persist",
          "theme": null
        },
        {
          "titre": "Nyinahin Catholic SHS teacher arrested after alleged student assault in viral video",
          "source": "MyJoyOnline (Ghana)",
          "cote": "F1",
          "lien": "https://www.myjoyonline.com/nyinahin-catholic-shs-teacher-arrested-after-alleged-student-assault-in-viral-video/",
          "theme": "S"
        }
      ],
      "enjeu": "Le Soudan est trop grand et trop divers pour qu'une victoire militaire d'un camp permette de gouverner. Toute issue militaire produira un État défaillant. Mais aucune négociation ne marche.",
      "consequencesAES": "Modérée (effet rebond Sahel) : Le BF subit la déstabilisation régionale et la concurrence pour l'attention humanitaire. : Aucun impact sécuritaire direct (distance géographique Soudan-BF ~3 500 km). · Possible diffusion modèle RSF/Janjaweed vers groupes sahéliens ? Pas documenté. · Réfugiés soudanai…",
      "lectureStructuree": "SITUATION (live) — 28 dépêches sur la période, dominante : Sécurité & défense, Politique interne & gouvernance.\nFaits saillants : « If Bardella wins: Scenarios for a far-right presidency in France » (ECFR — European Council on Foreign Relations, cote A2) ; « À partir de demain, la guerre en Ukraine sera aussi longue que la Première Guerre mondiale » (Le Grand Continent, cote A1) ; « Insecurity threatening Nigeria’s education future, says NUT president » (Vanguard (Nigeria), cote F2).\n\nENJEU CENTRAL — Le Soudan est trop grand et trop divers pour qu'une victoire militaire d'un camp permette de gouverner. Toute issue militaire produira un État défaillant. Mais aucune négociation ne marche.\n\nPOURQUOI — C'est la guerre la plus meurtrière du moment (~150 000 morts, 10 millions de déplacés, famine déclarée IPC 5) et pourtant la moins couverte. Elle illustre l'effondrement total d'un État de 48 millions d'habitants, alimenté par des sponsors régionaux (EAU vs Égypte/Arabie). Sa persistance déstabilise la mer Rouge, le Tchad, le Sud-Soudan, et révèle la faillite des médiations africaines et arabes.\n\nIMPACT POUR L'AES — Modérée (effet rebond Sahel) : Le BF subit la déstabilisation régionale et la concurrence pour l'attention humanitaire. : Aucun impact sécuritaire direct (distance géographique Soudan-BF ~3 500 km). · Possible diffusion modèle RSF/Janjaweed vers groupes sahéliens ? Pas documenté. · Réfugiés soudanai…\n\nSCÉNARIOS —\n• Tendanciel — partition de fait (50%) : SAF tient Nord/Centre/Est avec capitale Khartoum reprise. RSF tient Darfour/Kordofan-Sud. Pas d'accord politique. Économie effondrée. Crise humanitaire chronique. Pas de service public.\n• Recomposition — médiation Trump-Saoudite (20%) : Pression US (sanctions, déclaration génocide) force EAU à lâcher RSF. Médiation Saoudite-Égypte. Cessez-le-feu, cantonnement RSF. Transition militaire-civile négociée.\n\nÀ SURVEILLER — L'évolution du soutien émirien aux RSF face aux pressions US (génocide reconnu jan. 2025). ; Le sort d'El Fasher au Darfour (massacres documentés). ; La possibilité d'une base navale russe à Port-Soudan (recomposition mer Rouge).",
      "prospective": "12-24 mois : partition de fait probable. SAF contrôle Khartoum/Nord/Est, RSF contrôle Darfour/Kordofan-Sud.",
      "confiance": "eleve",
      "proseIA": null
    },
    "c_tai": {
      "id": "c_tai",
      "name": "Taïwan",
      "volume": 86,
      "themesDominants": [
        "Sécurité & défense",
        "Politique interne & gouvernance",
        "Justice & droit international"
      ],
      "faits": [
        {
          "titre": "If Bardella wins: Scenarios for a far-right presidency in France",
          "source": "ECFR — European Council on Foreign Relations",
          "cote": "A2",
          "lien": "https://ecfr.eu/publication/if-bardella-wins-scenarios-for-a-far-right-presidency-in-france/",
          "theme": "P"
        },
        {
          "titre": "Cour royale de Tiébélé: des femmes kassena gravent des valeurs culturelles",
          "source": "Sidwaya",
          "cote": "C2",
          "lien": "https://www.sidwaya.info/cour-royale-de-tiebele-des-femmes-kassena-gravent-des-valeurs-culturelles/",
          "theme": "S"
        },
        {
          "titre": "India's key objectives in Afghanistan solely driven by singular goal of destabilising Pakistan, envoy tells UNSC",
          "source": "Dawn (Pakistan)",
          "cote": "F2",
          "lien": "https://www.dawn.com/news/2006316/indias-key-objectives-in-afghanistan-solely-driven-by-singular-goal-of-destabilising-pakistan-envoy-tells-unsc",
          "theme": "S"
        },
        {
          "titre": "Kwankwasiyya dismisses reports of Kwankwaso’s exit from NDC",
          "source": "Vanguard (Nigeria)",
          "cote": "A2",
          "lien": "https://www.vanguardngr.com/2026/06/kwankwasiyya-dismisses-reports-of-kwankwasos-exit-from-ndc/",
          "theme": "J"
        },
        {
          "titre": "Trump says US helicopter pilots who went down in Strait of Hormuz are fine",
          "source": "Dawn (Pakistan)",
          "cote": "F1",
          "lien": "https://www.dawn.com/news/2006350/trump-says-us-helicopter-pilots-who-went-down-in-strait-of-hormuz-are-fine",
          "theme": "M"
        },
        {
          "titre": "Ouverture prochaine du Forum de coopération agro-technologique et industrielle Chine-Afrique 2026",
          "source": "Journal du Cameroun",
          "cote": "F2",
          "lien": "https://fr.journalducameroun.com/ouverture-prochaine-du-forum-de-cooperation-agro-technologique-et-industrielle-chine-afrique-2026/",
          "theme": "D"
        }
      ],
      "enjeu": "TSMC fait de Taïwan un nœud systémique de l'économie mondiale. Cela renforce la dissuasion (« bouclier de silicium ») mais aussi l'enjeu, donc la tentation chinoise de neutraliser cet avantage par la force.",
      "consequencesAES": "Élevée (impact macro mondial) : Une crise Taïwan = choc économique global qui frapperait le BF de plein fouet via les puces, l'inflation et le dollar. : Impact sécuritaire direct nul (Asie Pacifique). · Mais : crise Taïwan distrait attention US/UE → désengagement d'autres théâtres (Sahel, Sahel orie…",
      "lectureStructuree": "SITUATION (live) — 86 dépêches sur la période, dominante : Sécurité & défense, Politique interne & gouvernance, Justice & droit international.\nFaits saillants : « If Bardella wins: Scenarios for a far-right presidency in France » (ECFR — European Council on Foreign Relations, cote A2) ; « Cour royale de Tiébélé: des femmes kassena gravent des valeurs culturelles » (Sidwaya, cote C2) ; « India's key objectives in Afghanistan solely driven by singular goal of destabilising Pakistan, envoy tells UNSC » (Dawn (Pakistan), cote F2).\n\nENJEU CENTRAL — TSMC fait de Taïwan un nœud systémique de l'économie mondiale. Cela renforce la dissuasion (« bouclier de silicium ») mais aussi l'enjeu, donc la tentation chinoise de neutraliser cet avantage par la force.\n\nPOURQUOI — Une crise Taïwan ne serait pas régionale : ce serait l'équivalent de COVID + crise de 2008 combinés. Sans TSMC, l'IA, les smartphones, les voitures, la défense s'arrêtent en quelques mois. C'est aussi le test ultime de la primauté américaine en Pacifique : si Pékin gagne, la première chaîne d'îles tombe et l'ordre indo-pacifique bascule pour 50 ans.\n\nIMPACT POUR L'AES — Élevée (impact macro mondial) : Une crise Taïwan = choc économique global qui frapperait le BF de plein fouet via les puces, l'inflation et le dollar. : Impact sécuritaire direct nul (Asie Pacifique). · Mais : crise Taïwan distrait attention US/UE → désengagement d'autres théâtres (Sahel, Sahel orie…\n\nSCÉNARIOS —\n• Tendanciel — pression militaire constante, pas d'invasion (50%) : Pékin maintient pression militaire/économique/diplomatique. Taïwan se réarme. Économie mondiale absorbe coût continu de la « zone grise ». USA maintiennent ambiguïté.\n• Rupture — crise majeure non-cinétique (25%) : Blocus partiel ou « quarantaine » sanitaire/douanière. Test résolution US/alliés. Crise économique aiguë. Pas de guerre directe mais redéfinition règles.\n\nÀ SURVEILLER — Les exercices PLA majeurs (encerclement, blocus simulés). ; La position de Trump sur l'engagement militaire en cas d'invasion. ; Les avancées de TSMC en Arizona (relocalisation 100 Mds USD).",
      "prospective": "12-36 mois : pression militaire constante mais pas d'invasion immédiate. Risque crise non-cinétique (blocus, quarantaine).",
      "confiance": "eleve",
      "proseIA": null
    },
    "c_cod": {
      "id": "c_cod",
      "name": "RDC-Est",
      "volume": 28,
      "themesDominants": [
        "Sécurité & défense",
        "Politique interne & gouvernance",
        "Justice & droit international"
      ],
      "faits": [
        {
          "titre": "Burkina Faso: Des manipulateurs de drones kamikaze et des chefs terroristes tués",
          "source": "Net Afrique (BF)",
          "cote": "F2",
          "lien": "https://netafrique.net/burkina-faso-des-manipulateurs-de-drones-kamikaze-et-des-chefs-terroristes-tues/",
          "theme": "S"
        },
        {
          "titre": "Un prêtre congolais vivant en Italie appelle les Burkinabè à soutenir le Président Traoré",
          "source": "Net Afrique (BF)",
          "cote": "F2",
          "lien": "https://netafrique.net/un-pretre-congolais-vivant-en-italie-appelle-les-burkinabe-a-soutenir-le-president-traore/",
          "theme": "P"
        },
        {
          "titre": "Burkina : Le gouvernement suspend l’organisation des concours de beauté",
          "source": "Net Afrique (BF)",
          "cote": "F1",
          "lien": "https://netafrique.net/burkina-le-gouvernement-suspend-lorganisation-des-concours-de-beaute/",
          "theme": "P"
        },
        {
          "titre": "A Mambasa, l'effondrement du pont Ituri 2 paralyse le trafic sur la RN44",
          "source": "Radio Okapi (RDC)",
          "cote": "F2",
          "lien": "https://www.radiookapi.net/2026/06/09/actualite/societe/mambasa-leffondrement-du-pont-ituri-2-paralyse-le-trafic-sur-la-rn44",
          "theme": "S"
        },
        {
          "titre": "Eugène Rwamucyo, condamné à vingt-sept ans de prison pour « complicité de génocide » au Rwanda, revient devant la cour d’assises de Paris",
          "source": "Le Monde International",
          "cote": "B1",
          "lien": "https://www.lemonde.fr/afrique/article/2026/06/09/rwanda-eugene-rwamucyo-condamne-a-vingt-sept-ans-de-prison-pour-complicite-de-genocide-revient-devant-la-cour-d-assises-de-paris_6700090_3212.html",
          "theme": "J"
        },
        {
          "titre": "Burkina Faso : les autorités suspendent tous les concours de beauté",
          "source": "RT en français",
          "cote": "D4",
          "lien": "https://francais.rt.com/afrique/134966-burkina-faso-autorites-suspendent-tous-concours-beaute",
          "theme": "E"
        }
      ],
      "enjeu": "La RDC ne peut pas reconquérir le Kivu militairement seule. Le Rwanda ne peut pas annexer ouvertement sans crise diplomatique majeure. C'est un statu quo violent durable.",
      "consequencesAES": "Modérée (effet ressources critiques) : Le BF subit indirectement la crise du coltan et des minerais critiques, et observe avec intérêt le modèle d'État défaillant. : Pas d'impact sécuritaire direct (RDC à 2 500 km). · Mais : effet de précédent. Captation territoriale par voisin (Rwanda) sans réactio…",
      "lectureStructuree": "SITUATION (live) — 28 dépêches sur la période, dominante : Sécurité & défense, Politique interne & gouvernance, Justice & droit international.\nFaits saillants : « Burkina Faso: Des manipulateurs de drones kamikaze et des chefs terroristes tués » (Net Afrique (BF), cote F2) ; « Un prêtre congolais vivant en Italie appelle les Burkinabè à soutenir le Président Traoré » (Net Afrique (BF), cote F2) ; « Burkina : Le gouvernement suspend l’organisation des concours de beauté » (Net Afrique (BF), cote F1).\n\nENJEU CENTRAL — La RDC ne peut pas reconquérir le Kivu militairement seule. Le Rwanda ne peut pas annexer ouvertement sans crise diplomatique majeure. C'est un statu quo violent durable.\n\nPOURQUOI — C'est le théâtre de la longue guerre des Grands Lacs (~6 millions de morts cumulés depuis 1996). Au-delà de la dimension humanitaire (~7 millions de déplacés), le coltan congolais (70% production mondiale) est indispensable à toute l'industrie tech mondiale. La crise illustre aussi la captation des ressources africaines par procuration et l'échec total des médiations EAC, SADC, UA face à un agresseur — le Rwanda — protégé par sa mémoire post-génocide.\n\nIMPACT POUR L'AES — Modérée (effet ressources critiques) : Le BF subit indirectement la crise du coltan et des minerais critiques, et observe avec intérêt le modèle d'État défaillant. : Pas d'impact sécuritaire direct (RDC à 2 500 km). · Mais : effet de précédent. Captation territoriale par voisin (Rwanda) sans réactio…\n\nSCÉNARIOS —\n• Tendanciel — partition de fait (45%) : Kivu sous contrôle M23/Rwanda. Kinshasa garde reste mais perd autorité Est. Économie de prédation continue. ~7-10 M déplacés. Pas d'accord politique.\n• Escalade — guerre régionale (Burundi-Rwanda) (25%) : Engagement direct Burundi-Rwanda autour Sud-Kivu. Risque Ouganda en bascule. Lac Tanganyika nœud. ~5 M réfugiés supplémentaires. Implication EAC.\n\nÀ SURVEILLER — Les mouvements vers Bukavu et au-delà (Sud-Kivu vers Burundi). ; Les sanctions Trump sur le Rwanda (déclaration soutien M23 ?). ; Le sort de la MONUSCO (retrait achevé) et l'éventuelle nouvelle force africaine.",
      "prospective": "12-36 mois : partition de fait du Kivu. Kinshasa contrôle le reste mais perd autorité dans l'Est.",
      "confiance": "eleve",
      "proseIA": null
    },
    "c_yem": {
      "id": "c_yem",
      "name": "Mer Rouge",
      "volume": 28,
      "themesDominants": [
        "Diplomatie & alliances",
        "Maritime & océanique",
        "Économie & ressources"
      ],
      "faits": [
        {
          "titre": "Donald Trump enrage contre le Sultanat d’Oman !",
          "source": "Kapitalis (Tunisie)",
          "cote": "F2",
          "lien": "https://kapitalis.com/tunisie/2026/06/09/donald-trump-enrage-contre-le-sultanat-doman/",
          "theme": "D"
        },
        {
          "titre": "Trump says US helicopter pilots who went down in Strait of Hormuz are fine",
          "source": "Dawn (Pakistan)",
          "cote": "F1",
          "lien": "https://www.dawn.com/news/2006350/trump-says-us-helicopter-pilots-who-went-down-in-strait-of-hormuz-are-fine",
          "theme": "M"
        },
        {
          "titre": "Trump says in ‘final throes’ of reaching Middle East peace deal",
          "source": "Vanguard (Nigeria)",
          "cote": "F2",
          "lien": "https://www.vanguardngr.com/2026/06/trump-says-in-final-throes-of-reaching-middle-east-peace-deal/",
          "theme": "D"
        },
        {
          "titre": "Pak-Iran border trade halt to trigger LPG shortages",
          "source": "Dawn (Pakistan)",
          "cote": "F2",
          "lien": "https://www.dawn.com/news/2006250/pak-iran-border-trade-halt-to-trigger-lpg-shortages",
          "theme": "E"
        },
        {
          "titre": "‘I’m focused on my future,’ says African referee as FIFA confirms World Cup removal",
          "source": "Vanguard (Nigeria)",
          "cote": "F2",
          "lien": "https://www.vanguardngr.com/2026/06/im-focused-on-my-future-says-african-referee-as-fifa-confirms-world-cup-removal/",
          "theme": "J"
        },
        {
          "titre": "All 24 Indian crew rescued from tanker set ablaze off Oman after US strike",
          "source": "BBC World",
          "cote": "B1",
          "lien": "https://www.bbc.com/news/articles/cq51ep28165o?at_medium=RSS&at_campaign=rss",
          "theme": null
        }
      ],
      "enjeu": "Un acteur asymétrique armé de drones à 30 000 USD peut paralyser le commerce maritime mondial pendant des mois. C'est une révolution de l'asymétrie qui change toutes les doctrines navales.",
      "consequencesAES": "",
      "lectureStructuree": "SITUATION (live) — 28 dépêches sur la période, dominante : Diplomatie & alliances, Maritime & océanique, Économie & ressources.\nFaits saillants : « Donald Trump enrage contre le Sultanat d’Oman ! » (Kapitalis (Tunisie), cote F2) ; « Trump says US helicopter pilots who went down in Strait of Hormuz are fine » (Dawn (Pakistan), cote F1) ; « Trump says in ‘final throes’ of reaching Middle East peace deal » (Vanguard (Nigeria), cote F2).\n\nENJEU CENTRAL — Un acteur asymétrique armé de drones à 30 000 USD peut paralyser le commerce maritime mondial pendant des mois. C'est une révolution de l'asymétrie qui change toutes les doctrines navales.\n\nPOURQUOI — Bab el-Mandeb verrouille le passage entre Suez et l'océan Indien. Sa fermeture force les navires à contourner par le cap de Bonne-Espérance (+10-14 jours, +30% coût). Les frappes US-UK ne font pas reculer les Houthis, qui sortent renforcés (popularité gonflée, légitimité régionale, leçon utile pour tout acteur asymétrique). Cela impacte directement le commerce du Burkina Faso (importations Asie) et tous les pays enclavés du Sahel.\n\nÀ SURVEILLER — Le maintien ou la levée du blocus mer Rouge. ; Les négociations saoudo-houthies (gel possible ?). ; Le transfert de technologies iraniennes après l'effondrement de l'arc chiite.",
      "prospective": "6-18 mois : maintien du harcèlement maritime probable, sauf accord régional global.",
      "confiance": "eleve",
      "proseIA": null
    },
    "c_kor": {
      "id": "c_kor",
      "name": "Corée",
      "volume": 30,
      "themesDominants": [
        "Politique interne & gouvernance",
        "Diplomatie & alliances",
        "Sécurité & défense"
      ],
      "faits": [
        {
          "titre": "If Bardella wins: Scenarios for a far-right presidency in France",
          "source": "ECFR — European Council on Foreign Relations",
          "cote": "A2",
          "lien": "https://ecfr.eu/publication/if-bardella-wins-scenarios-for-a-far-right-presidency-in-france/",
          "theme": "P"
        },
        {
          "titre": "Why the Public Is Gravitating Toward the Hunter Biden Approach",
          "source": "The Atlantic",
          "cote": "F2",
          "lien": "https://www.theatlantic.com/newsletters/2026/06/jill-hunter-biden-social-media-posts/687476/?utm_source=feed",
          "theme": "P"
        },
        {
          "titre": "China's Xi hails deeper understanding at end of North Korea summit",
          "source": "Dawn (Pakistan)",
          "cote": "F2",
          "lien": "https://www.dawn.com/news/2006357/chinas-xi-hails-deeper-understanding-at-end-of-north-korea-summit",
          "theme": "D"
        },
        {
          "titre": "‘Israel violated Lebanon truce nearly 3,500 times’",
          "source": "Dawn (Pakistan)",
          "cote": "F2",
          "lien": "https://www.dawn.com/news/2006246/israel-violated-lebanon-truce-nearly-3500-times",
          "theme": "S"
        },
        {
          "titre": "Eating beetroots could prevent hypertension",
          "source": "MyJoyOnline (Ghana)",
          "cote": "F2",
          "lien": "https://www.myjoyonline.com/eating-beetroots-could-prevent-hypertension/",
          "theme": "E"
        },
        {
          "titre": "South Africa’s anti-migrant protests build ahead of local elections",
          "source": "Vanguard (Nigeria)",
          "cote": "F2",
          "lien": "https://www.vanguardngr.com/2026/06/south-africas-anti-migrant-protests-build-ahead-of-local-elections/",
          "theme": "P"
        }
      ],
      "enjeu": "L'axe Russie-Corée du Nord brise les sanctions internationales et démontre qu'un État-paria peut sortir de l'isolement en s'alignant sur une grande puissance révisionniste.",
      "consequencesAES": "",
      "lectureStructuree": "SITUATION (live) — 30 dépêches sur la période, dominante : Politique interne & gouvernance, Diplomatie & alliances, Sécurité & défense.\nFaits saillants : « If Bardella wins: Scenarios for a far-right presidency in France » (ECFR — European Council on Foreign Relations, cote A2) ; « Why the Public Is Gravitating Toward the Hunter Biden Approach » (The Atlantic, cote F2) ; « China's Xi hails deeper understanding at end of North Korea summit » (Dawn (Pakistan), cote F2).\n\nENJEU CENTRAL — L'axe Russie-Corée du Nord brise les sanctions internationales et démontre qu'un État-paria peut sortir de l'isolement en s'alignant sur une grande puissance révisionniste.\n\nPOURQUOI — Le pacte Russie-Corée du Nord (juin 2024) est la première véritable alliance entre une puissance nucléaire et un État-paria depuis longtemps. ~12 000 soldats nord-coréens en Koursk = première projection terrestre de Pyongyang depuis 1953. En échange, Moscou transfère des technologies qui font sauter les verrous sur le programme nord-coréen, augmentant directement la menace pour le Japon, la Corée du Sud et les États-Unis.\n\nÀ SURVEILLER — Les tirs balistiques de nouvelle génération. ; La diplomatie Trump-Kim (sommet possible ?). ; Le retour des troupes nord-coréennes de Russie avec expérience combat.",
      "prospective": "12-24 mois : poursuite du rapprochement RU-PRK, renforcement programmes, peut-être test nucléaire.",
      "confiance": "eleve",
      "proseIA": null
    },
    "c_syr": {
      "id": "c_syr",
      "name": "Syrie",
      "volume": 41,
      "themesDominants": [
        "Diplomatie & alliances",
        "Sécurité & défense",
        "Politique interne & gouvernance"
      ],
      "faits": [
        {
          "titre": "If Bardella wins: Scenarios for a far-right presidency in France",
          "source": "ECFR — European Council on Foreign Relations",
          "cote": "A2",
          "lien": "https://ecfr.eu/publication/if-bardella-wins-scenarios-for-a-far-right-presidency-in-france/",
          "theme": "P"
        },
        {
          "titre": "Mobilité des étudiants : Vers un protocole d’accord entre le Burkina et le Ghana",
          "source": "Net Afrique (BF)",
          "cote": "F2",
          "lien": "https://netafrique.net/mobilite-des-etudiants-vers-un-protocole-daccord-entre-le-burkina-et-le-ghana/",
          "theme": "D"
        },
        {
          "titre": "À partir de demain, la guerre en Ukraine sera aussi longue que la Première Guerre mondiale",
          "source": "Le Grand Continent",
          "cote": "A1",
          "lien": "https://legrandcontinent.eu/fr/2026/06/09/a-partir-de-demain-la-guerre-en-ukraine-sera-aussi-longue-que-la-premiere-guerre-mondiale/",
          "theme": "S"
        },
        {
          "titre": "PANDEF hails NDC as emerging National Political Force",
          "source": "Vanguard (Nigeria)",
          "cote": "F2",
          "lien": "https://www.vanguardngr.com/2026/06/pandef-hails-ndc-as-emerging-national-political-force/",
          "theme": "D"
        },
        {
          "titre": "India's key objectives in Afghanistan solely driven by singular goal of destabilising Pakistan, envoy tells UNSC",
          "source": "Dawn (Pakistan)",
          "cote": "F2",
          "lien": "https://www.dawn.com/news/2006316/indias-key-objectives-in-afghanistan-solely-driven-by-singular-goal-of-destabilising-pakistan-envoy-tells-unsc",
          "theme": "S"
        },
        {
          "titre": "Donald Trump enrage contre le Sultanat d’Oman !",
          "source": "Kapitalis (Tunisie)",
          "cote": "F2",
          "lien": "https://kapitalis.com/tunisie/2026/06/09/donald-trump-enrage-contre-le-sultanat-doman/",
          "theme": "D"
        }
      ],
      "enjeu": "La transition syrienne peut reconstruire un État viable (rare) ou se fragmenter en libanisation (probable). La gestion de la question kurde et le retour des réfugiés sont les vraies épreuves.",
      "consequencesAES": "",
      "lectureStructuree": "SITUATION (live) — 41 dépêches sur la période, dominante : Diplomatie & alliances, Sécurité & défense, Politique interne & gouvernance.\nFaits saillants : « If Bardella wins: Scenarios for a far-right presidency in France » (ECFR — European Council on Foreign Relations, cote A2) ; « Mobilité des étudiants : Vers un protocole d’accord entre le Burkina et le Ghana » (Net Afrique (BF), cote F2) ; « À partir de demain, la guerre en Ukraine sera aussi longue que la Première Guerre mondiale » (Le Grand Continent, cote A1).\n\nENJEU CENTRAL — La transition syrienne peut reconstruire un État viable (rare) ou se fragmenter en libanisation (probable). La gestion de la question kurde et le retour des réfugiés sont les vraies épreuves.\n\nPOURQUOI — La Syrie était le pilier oriental de l'arc chiite iranien et de la projection russe en Méditerranée (base Tartous). Sa chute reconfigure tout le Levant : Iran isolé, Russie affaiblie, Hezbollah privé de corridor logistique, Turquie en position de force. Mais HTS reste suspect (passé jihadiste), la question kurde non résolue, Israël a détruit 80% des capacités militaires syriennes en 48h post-Assad.\n\nÀ SURVEILLER — Les négociations HTS-SDF sur l'avenir des Kurdes. ; La levée ou non des sanctions occidentales sur le nouveau régime. ; Le retour des réfugiés syriens depuis Turquie/Liban (~6 millions).",
      "prospective": "6-12 mois : stabilisation fragile ou fragmentation. Décision cruciale sur Kurdes.",
      "confiance": "eleve",
      "proseIA": null
    }
  },
  "syntheseExecutive": "Sur la période, 800 dépêches ont été classées et cotées. Priorité géographique : 1. Sahel & AO franco. (74 signaux, tendance stable). Ruptures repérées : Ouagadougou : L’effondrement de la dalle d’un bâtiment R+1 fait des victimes ; Guerre au Moyen-Orient : les négociateurs s’activent malgré l’escalade militaire. Signaux faibles émergents à surveiller : 13. Asie du Sud-Est · Diplomatie & alliances ; 3. Afrique centrale · Maritime & océanique ; 11. Asie centrale · Sécurité & défense.\n\nSujets chauds de la période :\n• Iran-Israël (148 signaux) — La question nucléaire iranienne et la survie du régime des Pasdaran détermineront la stabilité régionale pour 20 ans.\n• Gaza-Liban (99 signaux) — Sans horizon politique palestinien crédible (deux États ou alternative), aucun cessez-le-feu ne sera durable. Le « jour d'après » est la vraie question, pas le « jour pendant ».\n• Sahel/AES (91 signaux) — Inventer un modèle politique africain qui combine souveraineté affichée et efficacité sécuritaire — sans y être encore parvenu.",
  "llmUsed": false,
  "achSuggestions": [
    {
      "conflictId": "c_iran_il",
      "name": "Iran-Israël",
      "hypotheses": [
        "Iran-Israël : escalade / aggravation a 3-6 mois",
        "Iran-Israël : statu quo instable",
        "Iran-Israël : desescalade / reglement partiel"
      ],
      "evidence": [
        "If Bardella wins: Scenarios for a far-right presidency in France",
        "Cyclisme : Le Tour du Faso réintègre le circuit international UCI",
        "Guerre au Moyen-Orient : les négociateurs s’activent malgré l’escalade militaire",
        "Alleged rigging: Stop grandstanding, bring your evidence, Atiku dares ex-SGF Lawal",
        "2027: Nigeria must move beyond North-South politics, says Baba-Ahmed"
      ]
    },
    {
      "conflictId": "c_gaza",
      "name": "Gaza-Liban",
      "hypotheses": [
        "Gaza-Liban : escalade / aggravation a 3-6 mois",
        "Gaza-Liban : statu quo instable",
        "Gaza-Liban : desescalade / reglement partiel"
      ],
      "evidence": [
        "If Bardella wins: Scenarios for a far-right presidency in France",
        "Guerre au Moyen-Orient : les négociateurs s’activent malgré l’escalade militaire",
        "Gaza: les ordres d'évacuation créent un vent de panique chez les Gazaouis",
        "India's key objectives in Afghanistan solely driven by singular goal of destabilising Pakistan, envoy tells UNSC",
        "Donald Trump enrage contre le Sultanat d’Oman !"
      ]
    },
    {
      "conflictId": "c_aes",
      "name": "Sahel/AES",
      "hypotheses": [
        "Sahel/AES : escalade / aggravation a 3-6 mois",
        "Sahel/AES : statu quo instable",
        "Sahel/AES : desescalade / reglement partiel"
      ],
      "evidence": [
        "If Bardella wins: Scenarios for a far-right presidency in France",
        "Ouagadougou : L’effondrement de la dalle d’un bâtiment R+1 fait des victimes",
        "Drame à Ouagadougou : Un mort et sept blessés dans l’effondrement d’un bâtiment en chantier à Kouba",
        "Burkina Faso: Des manipulateurs de drones kamikaze et des chefs terroristes tués",
        "Pr Youssoufou Ouédraogo, enseignant d'université à la retraite : « Être fort, c'est être capable de s'arrêter à un feu tricolore à minuit, alors que personne ne vous regarde »"
      ]
    }
  ],
  "agentLog": [
    {
      "at": "2026-06-09T10:37:42.779Z",
      "agent": "Agent Analyste",
      "message": "Demarrage (IA: non, mode structure)"
    },
    {
      "at": "2026-06-09T10:37:42.806Z",
      "agent": "Agent Analyste",
      "message": "10 conflits charges"
    },
    {
      "at": "2026-06-09T10:37:42.806Z",
      "agent": "Agent Analyste",
      "message": "800 articles dans la fenetre (168 h)"
    },
    {
      "at": "2026-06-09T10:37:42.811Z",
      "agent": "Agent Analyste",
      "message": "Detection: 9 tendances, 8 signaux faibles, 8 ruptures, 0 recompositions"
    },
    {
      "at": "2026-06-09T10:37:42.893Z",
      "agent": "Agent Analyste",
      "message": "10 conflits analyses, 3 suggestions ACH"
    },
    {
      "at": "2026-06-09T10:37:42.893Z",
      "agent": "Agent Analyste",
      "message": "Productions: 3 notes zone, 3 prospectives, 4 etudes"
    }
  ]
}